[
  {
   "name": "How to Train Your Dragon อภินิหารไวกิ้งพิชิตมังกร (2025)",
   "info": "พากย์ไทย",
   "image": "https://img.fw4free.com/postor/20250611223515q5pXRYTycaeW6dEgsCrd4mYPmxM.jpg",
   "subtitle": "https://pastebin.com/raw/XjDpyhzb",
   "url": "https://m1free.inwstream.com:1936/movie4/How_to_Train_Your_Dragon_2025/How_to_Train_Your_Dragon_2025_th_1080.mp4/playlist.m3u8",
   "referer": "https://fw4free.com/"
  },
  {
   "name": "How to Train Your Dragon อภินิหารไวกิ้งพิชิตมังกร (2025)",
   "info": "บรรยายไทย",
   "image": "https://img.fw4free.com/postor/20250611223515q5pXRYTycaeW6dEgsCrd4mYPmxM.jpg",
   "subtitle": "https://pastebin.com/raw/XjDpyhzb",
   "url": "https://m1free.inwstream.com:1936/movie4/How_to_Train_Your_Dragon_2025/How_to_Train_Your_Dragon_2025_st_1080_T.mp4/playlist.m3u8",
   "referer": "https://fw4free.com/"
  },
  {
   "name": "Speak (2004)",
   "info": "บรรยายไทย",
   "image": "https://img.fw4free.com/postor/20250721032210kxQ9lRgC3tMVNPzLMFsiOK8H8fn.jpg",
   "subtitle": "https://pastebin.com/raw/XjDpyhzb",
   "url": "https://m1free.inwstream.com:1936/movie4/Speak_2004/Speak_2004_st_1080_AI.mp4/playlist.m3u8",
   "referer": "https://fw4free.com/"
  },
  {
   "name": "The Adventures of Buratino (Priklyucheniya Buratino)",
   "info": "บรรยายไทย",
   "image": "https://img.fw4free.com/postor/20250721031741rX1ENcjIOu89VHdkRTTFa8F18kM.jpg",
   "subtitle": "https://pastebin.com/raw/XjDpyhzb",
   "url": "https://m1free.inwstream.com:1936/movie4/The_Adventures_of_Buratino_1976/The_Adventures_of_Buratino_1976_st_1080_AI.mp4/playlist.m3u8",
   "referer": "https://fw4free.com/"
  },
  {
   "name": "Dora and the Search for Sol Dorado ดอร่ากับการตามหาพระอาทิตย์สีทอง (2025)",
   "info": "บรรยายไทย",
   "image": "https://img.fw4free.com/postor/20250721031247r3d6u2n7iPoWNsSWwlJJWrDblOH.jpg",
   "subtitle": "https://pastebin.com/raw/XjDpyhzb",
   "url": "https://m1free.inwstream.com:1936/movie4/Dora_and_the_Search_for_Sol_Dorado_2025/Dora_and_the_Search_for_Sol_Dorado_2025_st_1080.mp4/playlist.m3u8",
   "referer": "https://fw4free.com/"
  },
  {
   "name": "Alarum คู่เดือดโคตรคนระห่ำ (2025)",
   "info": "พากย์ไทย",
   "image": "https://img.fw4free.com/postor/20250719113813ckyYZf5cGTSOwF8LWIRqeThyh18.jpg",
   "subtitle": "https://pastebin.com/raw/XjDpyhzb",
   "url": "https://m1free.inwstream.com:1936/movie4/Alarum_2025/Alarum_2025_TH_1080p.mp4/playlist.m3u8",
   "referer": "https://fw4free.com/"
  },
  {
   "name": "Alarum คู่เดือดโคตรคนระห่ำ (2025)",
   "info": "บรรยายไทย",
   "image": "https://img.fw4free.com/postor/20250719113813ckyYZf5cGTSOwF8LWIRqeThyh18.jpg",
   "subtitle": "https://pastebin.com/raw/XjDpyhzb",
   "url": "https://m1free.inwstream.com:1936/movie4/Alarum_2025/Alarum_2025_EN_1080p.mp4/playlist.m3u8",
   "referer": "https://fw4free.com/"
  },
  {
   "name": "I'm Still a Superstar (Sigo siendo la misma)",
   "info": "บรรยายไทย",
   "image": "https://img.fw4free.com/postor/202507181522297kkydknXOD67CCU6iLxgL0hcCdL.jpg",
   "subtitle": "https://pastebin.com/raw/XjDpyhzb",
   "url": "https://m1free.inwstream.com:1936/movie4/I_m_Still_a_Superstar_2025/I_m_Still_a_Superstar_2025_ST_1080p.mp4/playlist.m3u8",
   "referer": "https://fw4free.com/"
  },
  {
   "name": "Almost Family (Família, Pero No Mucho)",
   "info": "บรรยายไทย",
   "image": "https://img.fw4free.com/postor/20250718150711sJTEJDlUwuXet2s8Ou6MUryqpQh.jpg",
   "subtitle": "https://pastebin.com/raw/XjDpyhzb",
   "url": "https://m1free.inwstream.com:1936/movie4/Almost_Family_2025/Almost_Family_2025_ST_1080p.mp4/playlist.m3u8",
   "referer": "https://fw4free.com/"
  },
  {
   "name": "The Amateur ร้ายสมัครเล่น (2025)",
   "info": "พากย์ไทย",
   "image": "https://img.fw4free.com/postor/202504152244222grhfMw97MGbat6aH4lFSUnVDFE.jpg",
   "subtitle": "https://pastebin.com/raw/XjDpyhzb",
   "url": "https://m1free.inwstream.com:1936/movie4/The_Amateur_2025/The_Amateur_2025_TH_1080p.mp4/playlist.m3u8",
   "referer": "https://fw4free.com/"
  },
  {
   "name": "The Amateur ร้ายสมัครเล่น (2025)",
   "info": "บรรยายไทย",
   "image": "https://img.fw4free.com/postor/202504152244222grhfMw97MGbat6aH4lFSUnVDFE.jpg",
   "subtitle": "https://pastebin.com/raw/XjDpyhzb",
   "url": "https://m1free.inwstream.com:1936/movie4/The_Amateur_2025/The_Amateur_2025_EN_1080p.mp4/playlist.m3u8",
   "referer": "https://fw4free.com/"
  },
  {
   "name": "Karate Kid: Legends คาราเต้ คิด ผนึกพลังตำนานนักสู้ (2025)",
   "info": "พากย์ไทยโรง",
   "image": "https://img.fw4free.com/postor/20250709195943AEgggzRr1vZCLY86MAp93li43z.jpg",
   "subtitle": "https://pastebin.com/raw/XjDpyhzb",
   "url": "https://m1free.inwstream.com:1936/movie4/Karate_Kid_Legends_2025/Karate_Kid_Legends_2025_thr_z1.mp4/playlist.m3u8",
   "referer": "https://fw4free.com/"
  },
  {
   "name": "Karate Kid: Legends คาราเต้ คิด ผนึกพลังตำนานนักสู้ (2025)",
   "info": "บรรยายไทย",
   "image": "https://img.fw4free.com/postor/20250709195943AEgggzRr1vZCLY86MAp93li43z.jpg",
   "subtitle": "https://pastebin.com/raw/XjDpyhzb",
   "url": "https://m1free.inwstream.com:1936/movie4/Karate_Kid_Legends_2025/Karate_Kid_Legends_2025_st_1080.mp4/playlist.m3u8",
   "referer": "https://fw4free.com/"
  },
  {
   "name": "Trainwreck: Balloon Boy อภิมหาวายป่วง: บอลลูนบอย (2025)",
   "info": "พากย์ไทย",
   "image": "https://img.fw4free.com/postor/202507160803274QpWZlGZMYrAnlQizjVIMnAXnv0.jpg",
   "subtitle": "https://pastebin.com/raw/XjDpyhzb",
   "url": "https://m1free.inwstream.com:1936/movie4/Trainwreck_Balloon_Boy_2025/Trainwreck_Balloon_Boy_2025_TH_1080p.mp4/playlist.m3u8",
   "referer": "https://fw4free.com/"
  },
  {
   "name": "Trainwreck: Balloon Boy อภิมหาวายป่วง: บอลลูนบอย (2025)",
   "info": "บรรยายไทย",
   "image": "https://img.fw4free.com/postor/202507160803274QpWZlGZMYrAnlQizjVIMnAXnv0.jpg",
   "subtitle": "https://pastebin.com/raw/XjDpyhzb",
   "url": "https://m1free.inwstream.com:1936/movie4/Trainwreck_Balloon_Boy_2025/Trainwreck_Balloon_Boy_2025_EN_1080p.mp4/playlist.m3u8",
   "referer": "https://fw4free.com/"
  },
  {
   "name": "Apocalypse in the Tropics วันสิ้นโลกในเขตร้อน (2025)",
   "info": "บรรยายไทย",
   "image": "https://img.fw4free.com/postor/20250715080452w3jnacmMmfOem8RAgz9h1h1T4Wa.jpg",
   "subtitle": "https://pastebin.com/raw/XjDpyhzb",
   "url": "https://m1free.inwstream.com:1936/movie4/Apocalypse_in_the_Tropics_2025/Apocalypse_in_the_Tropics_2025_ST_1080p.mp4/playlist.m3u8",
   "referer": "https://fw4free.com/"
  },
  {
   "name": "Baghead ผีสิงผี (2023)",
   "info": "พากย์ไทย",
   "image": "https://img.fw4free.com/postor/20250605083237lbOyeiiRYAE6Nm2e7xiNAAaRwZB.jpg",
   "subtitle": "https://pastebin.com/raw/XjDpyhzb",
   "url": "https://m1free.inwstream.com:1936/movie4/Baghead_2023/Baghead_2023_TH_1080p_1.mp4/playlist.m3u8",
   "referer": "https://fw4free.com/"
  },
  {
   "name": "Baghead ผีสิงผี (2023)",
   "info": "บรรยายไทย",
   "image": "https://img.fw4free.com/postor/20250605083237lbOyeiiRYAE6Nm2e7xiNAAaRwZB.jpg",
   "subtitle": "https://pastebin.com/raw/XjDpyhzb",
   "url": "https://m1free.inwstream.com:1936/movie4/Baghead_2023/Baghead_2023_EN_1080p_1.mp4/playlist.m3u8",
   "referer": "https://fw4free.com/"
  },
  {
   "name": "Mountainhead เมาน์เทนเฮด (2025)",
   "info": "พากย์ไทย",
   "image": "https://img.fw4free.com/postor/20250602110257jZKK5mFKWbquxhAGMkRJtNYwk0I.jpg",
   "subtitle": "https://pastebin.com/raw/XjDpyhzb",
   "url": "https://m1free.inwstream.com:1936/movie4/Mountainhead_2025/Mountainhead_2025_TH_1080p.mp4/playlist.m3u8",
   "referer": "https://fw4free.com/"
  },
  {
   "name": "Mountainhead เมาน์เทนเฮด (2025)",
   "info": "บรรยายไทย",
   "image": "https://img.fw4free.com/postor/20250602110257jZKK5mFKWbquxhAGMkRJtNYwk0I.jpg",
   "subtitle": "https://pastebin.com/raw/XjDpyhzb",
   "url": "https://m1free.inwstream.com:1936/movie4/Mountainhead_2025/Mountainhead_2025_EN_1080p.mp4/playlist.m3u8",
   "referer": "https://fw4free.com/"
  },
  {
   "name": "Anora อโนรา (2024)",
   "info": "พากย์ไทย",
   "image": "https://img.fw4free.com/postor/202501261052217MrgIUeq0DD2iF7GR6wqJfYZNeC.jpg",
   "subtitle": "https://pastebin.com/raw/XjDpyhzb",
   "url": "https://m1free.inwstream.com:1936/movie4/Anora_2024/Anora_2024_TH_1080p.mp4/playlist.m3u8",
   "referer": "https://fw4free.com/"
  },
  {
   "name": "Anora อโนรา (2024)",
   "info": "บรรยายไทย",
   "image": "https://img.fw4free.com/postor/202501261052217MrgIUeq0DD2iF7GR6wqJfYZNeC.jpg",
   "subtitle": "https://pastebin.com/raw/XjDpyhzb",
   "url": "https://m1free.inwstream.com:1936/movie4/Anora_2024/Anora_2024_st_1080.mp4/playlist.m3u8",
   "referer": "https://fw4free.com/"
  },
  {
   "name": "Z-O-M-B-I-E-S 3 (Zombies 3)",
   "info": "พากย์ไทย",
   "image": "https://img.fw4free.com/postor/20250713050209qFSJ0qOe4j7p2KkEBHjYM3htNr8.jpg",
   "subtitle": "https://pastebin.com/raw/XjDpyhzb",
   "url": "https://m1free.inwstream.com:1936/movie3/Z_O_M_B_I_E_S_3_2022/Z_O_M_B_I_E_S_3_2022_th_1080.mp4/playlist.m3u8",
   "referer": "https://fw4free.com/"
  },
  {
   "name": "Z-O-M-B-I-E-S 3 (Zombies 3)",
   "info": "บรรยายไทย",
   "image": "https://img.fw4free.com/postor/20250713050209qFSJ0qOe4j7p2KkEBHjYM3htNr8.jpg",
   "subtitle": "https://pastebin.com/raw/XjDpyhzb",
   "url": "https://m1free.inwstream.com:1936/movie3/Z_O_M_B_I_E_S_3_2022/Z_O_M_B_I_E_S_3_2022_st_1080.mp4/playlist.m3u8",
   "referer": "https://fw4free.com/"
  },
  {
   "name": "Z-O-M-B-I-E-S 2 (Zombies 2)",
   "info": "พากย์ไทย",
   "image": "https://img.fw4free.com/postor/20250713045718hUXKuy6jjhJQHfb2hYyeupyDnZk.jpg",
   "subtitle": "https://pastebin.com/raw/XjDpyhzb",
   "url": "https://m1free.inwstream.com:1936/movie3/Z_O_M_B_I_E_S_2_2020/Z_O_M_B_I_E_S_2_2020_TH_1080p.mp4/playlist.m3u8",
   "referer": "https://fw4free.com/"
  },
  {
   "name": "Z-O-M-B-I-E-S 2 (Zombies 2)",
   "info": "บรรยายไทย",
   "image": "https://img.fw4free.com/postor/20250713045718hUXKuy6jjhJQHfb2hYyeupyDnZk.jpg",
   "subtitle": "https://pastebin.com/raw/XjDpyhzb",
   "url": "https://m1free.inwstream.com:1936/movie3/Z_O_M_B_I_E_S_2_2020/Z_O_M_B_I_E_S_2_2020_st_1080.mp4/playlist.m3u8",
   "referer": "https://fw4free.com/"
  },
  {
   "name": "Z-O-M-B-I-E-S (Zombies)",
   "info": "พากย์ไทย",
   "image": "https://img.fw4free.com/postor/20250713045229snGVInrnUBK6LrfLZkOdbj5PpJo.jpg",
   "subtitle": "https://pastebin.com/raw/XjDpyhzb",
   "url": "https://m1free.inwstream.com:1936/movie3/Z_O_M_B_I_E_S_2018/Z_O_M_B_I_E_S_2018_TH_1080p.mp4/playlist.m3u8",
   "referer": "https://fw4free.com/"
  },
  {
   "name": "Z-O-M-B-I-E-S (Zombies)",
   "info": "บรรยายไทย",
   "image": "https://img.fw4free.com/postor/20250713045229snGVInrnUBK6LrfLZkOdbj5PpJo.jpg",
   "subtitle": "https://pastebin.com/raw/XjDpyhzb",
   "url": "https://m1free.inwstream.com:1936/movie3/Z_O_M_B_I_E_S_2018/Z_O_M_B_I_E_S_2018_st_1080.mp4/playlist.m3u8",
   "referer": "https://fw4free.com/"
  },
  {
   "name": "Jaws @ 50: The Definitive Inside Story (2025)",
   "info": "บรรยายไทย",
   "image": "https://img.fw4free.com/postor/20250712080938nTox8VgVh3Rqar2yVk6aRTzoh69.jpg",
   "subtitle": "https://pastebin.com/raw/XjDpyhzb",
   "url": "https://m1free.inwstream.com:1936/movie4/JAWS_at_50_The_Definitive_Inside_Story_2025/JAWS_at_50_The_Definitive_Inside_Story_2025_EN_1080p.mp4/playlist.m3u8",
   "referer": "https://fw4free.com/"
  },
  {
   "name": "Zombies 4: Dawn of the Vampires (2025)",
   "info": "บรรยายไทย",
   "image": "https://img.fw4free.com/postor/202507120739356rGsqBxI4r1YkS9FuraovWi465w.jpg",
   "subtitle": "https://pastebin.com/raw/XjDpyhzb",
   "url": "https://m1free.inwstream.com:1936/movie4/Zombies_4_Dawn_of_the_Vampires_2025/Zombies_4_Dawn_of_the_Vampires_2025_EN_1080p.mp4/playlist.m3u8",
   "referer": "https://fw4free.com/"
  },
  {
   "name": "The Phoenician Scheme แผนลับซ่อนร้าย (2025)",
   "info": "บรรยายไทย",
   "image": "https://img.fw4free.com/postor/20250711222112jtEqpy0K1iVuCebRwWqT6BZ6jLN.jpg",
   "subtitle": "https://pastebin.com/raw/XjDpyhzb",
   "url": "https://m1free.inwstream.com:1936/movie4/The_Phoenician_Scheme_2025/The_Phoenician_Scheme_2025_st_1080.mp4/playlist.m3u8",
   "referer": "https://fw4free.com/"
  },
  {
   "name": "Madea's Destination Wedding ป้าลุยแหลกแหกวิวาห์ป่วน (2025)",
   "info": "พากย์ไทย",
   "image": "https://img.fw4free.com/postor/202507111532072hxwRxLqyD1szQTgQK3o7yPF7Ob.jpg",
   "subtitle": "https://pastebin.com/raw/XjDpyhzb",
   "url": "https://m1free.inwstream.com:1936/movie4/Madea_s_Destination_Wedding_2025/Madea_s_Destination_Wedding_2025_TH_1080p.mp4/playlist.m3u8",
   "referer": "https://fw4free.com/"
  },
  {
   "name": "Madea's Destination Wedding ป้าลุยแหลกแหกวิวาห์ป่วน (2025)",
   "info": "บรรยายไทย",
   "image": "https://img.fw4free.com/postor/202507111532072hxwRxLqyD1szQTgQK3o7yPF7Ob.jpg",
   "subtitle": "https://pastebin.com/raw/XjDpyhzb",
   "url": "https://m1free.inwstream.com:1936/movie4/Madea_s_Destination_Wedding_2025/Madea_s_Destination_Wedding_2025_EN_1080p.mp4/playlist.m3u8",
   "referer": "https://fw4free.com/"
  },
  {
   "name": "Almost Cops (Bad Boa's)",
   "info": "พากย์ไทย",
   "image": "https://img.fw4free.com/postor/20250711150853v3aq0JZIjXr8okdnBR7yzn9kcbd.jpg",
   "subtitle": "https://pastebin.com/raw/XjDpyhzb",
   "url": "https://m1free.inwstream.com:1936/movie4/Almost_Cops_2025/Almost_Cops_2025_TH_1080p.mp4/playlist.m3u8",
   "referer": "https://fw4free.com/"
  },
  {
   "name": "Almost Cops (Bad Boa's)",
   "info": "บรรยายไทย",
   "image": "https://img.fw4free.com/postor/20250711150853v3aq0JZIjXr8okdnBR7yzn9kcbd.jpg",
   "subtitle": "https://pastebin.com/raw/XjDpyhzb",
   "url": "https://m1free.inwstream.com:1936/movie4/Almost_Cops_2025/Almost_Cops_2025_ST_1080p.mp4/playlist.m3u8",
   "referer": "https://fw4free.com/"
  },
  {
   "name": "Brick กำแพง (2025)",
   "info": "พากย์ไทย",
   "image": "https://img.fw4free.com/postor/2025071014453973VFU1frjqS2XmSD8FCvADADf7M.jpg",
   "subtitle": "https://pastebin.com/raw/XjDpyhzb",
   "url": "https://m1free.inwstream.com:1936/movie4/Brick_2025/Brick_2025_TH_1080p.mp4/playlist.m3u8",
   "referer": "https://fw4free.com/"
  },
  {
   "name": "Brick กำแพง (2025)",
   "info": "บรรยายไทย",
   "image": "https://img.fw4free.com/postor/2025071014453973VFU1frjqS2XmSD8FCvADADf7M.jpg",
   "subtitle": "https://pastebin.com/raw/XjDpyhzb",
   "url": "https://m1free.inwstream.com:1936/movie4/Brick_2025/Brick_2025_ST_1080p.mp4/playlist.m3u8",
   "referer": "https://fw4free.com/"
  },
  {
   "name": "Karate Kid: Legends คาราเต้ คิด ผนึกพลังตำนานนักสู้ (2025)",
   "info": "บรรยายไทย",
   "image": "https://img.fw4free.com/postor/20250709195943AEgggzRr1vZCLY86MAp93li43z.jpg",
   "subtitle": "https://pastebin.com/raw/XjDpyhzb",
   "url": "https://m1free.inwstream.com:1936/movie4/Karate_Kid_Legends_2025/Karate_Kid_Legends_2025_st_1080.mp4/playlist.m3u8",
   "referer": "https://fw4free.com/"
  },
  {
   "name": "Hell of a Summer ค่ายเฮี้ยน...เพี้ยนยันฆาตรกร (2023)",
   "info": "บรรยายไทย",
   "image": "https://img.fw4free.com/postor/20250709195709wmSCSKUI15Q2pApB5f3oEl0EQuE.jpg",
   "subtitle": "https://pastebin.com/raw/XjDpyhzb",
   "url": "https://m1free.inwstream.com:1936/movie4/Hell_of_a_Summer_2023/Hell_of_a_Summer_2023_st_1080.mp4/playlist.m3u8",
   "referer": "https://fw4free.com/"
  },
  {
   "name": "Damage ปรารถนาลึกสุดใจ (1992)",
   "info": "พากย์ไทย",
   "image": "https://img.fw4free.com/postor/20250709194702G2cd788qrBKPwxOZsMRWR9zvl1.jpg",
   "subtitle": "https://pastebin.com/raw/XjDpyhzb",
   "url": "https://m1free.inwstream.com:1936/movie4/Damage_1992/Damage_1992_th_1080.mp4/playlist.m3u8",
   "referer": "https://fw4free.com/"
  },
  {
   "name": "The Image of You รักซ้อนซ่อนจิต (2024)",
   "info": "บรรยายไทย",
   "image": "https://img.fw4free.com/postor/20250709150244gboq2oB6QNBcW32V0A8uOajTwXU.jpg",
   "subtitle": "https://pastebin.com/raw/XjDpyhzb",
   "url": "https://m1free.inwstream.com:1936/movie4/The_Image_of_You_2024/The_Image_of_You_2024_EN_1080p.mp4/playlist.m3u8",
   "referer": "https://fw4free.com/"
  },
  {
   "name": "The Immigrant ลี้ภัยร้าย พ่ายภัยรัก (2013)",
   "info": "พากย์ไทย",
   "image": "https://img.fw4free.com/postor/2025070911131187Hk1gEudZQWgq6pU8rJt1Xfpg7.jpg",
   "subtitle": "https://pastebin.com/raw/XjDpyhzb",
   "url": "https://m1free.inwstream.com:1936/movie4/The_Immigrant_2013/The_Immigrant_2013_TH_1080p.mp4/playlist.m3u8",
   "referer": "https://fw4free.com/"
  },
  {
   "name": "The Immigrant ลี้ภัยร้าย พ่ายภัยรัก (2013)",
   "info": "บรรยายไทย",
   "image": "https://img.fw4free.com/postor/2025070911131187Hk1gEudZQWgq6pU8rJt1Xfpg7.jpg",
   "subtitle": "https://pastebin.com/raw/XjDpyhzb",
   "url": "https://m1free.inwstream.com:1936/movie4/The_Immigrant_2013/The_Immigrant_2013_EN_1080p.mp4/playlist.m3u8",
   "referer": "https://fw4free.com/"
  },
  {
   "name": "Domino โดมิโน สวยโคตรมหากาฬ (2005)",
   "info": "พากย์ไทย",
   "image": "https://img.fw4free.com/postor/20250709101724pZdIfYkM5kV5BaUDYzwzgmpUxno.jpg",
   "subtitle": "https://pastebin.com/raw/XjDpyhzb",
   "url": "https://m1free.inwstream.com:1936/movie4/Domino_2005/Domino_2005_TH_1080p.mp4/playlist.m3u8",
   "referer": "https://fw4free.com/"
  },
  {
   "name": "Domino โดมิโน สวยโคตรมหากาฬ (2005)",
   "info": "บรรยายไทย",
   "image": "https://img.fw4free.com/postor/20250709101724pZdIfYkM5kV5BaUDYzwzgmpUxno.jpg",
   "subtitle": "https://pastebin.com/raw/XjDpyhzb",
   "url": "https://m1free.inwstream.com:1936/movie4/Domino_2005/Domino_2005_EN_1080p.mp4/playlist.m3u8",
   "referer": "https://fw4free.com/"
  },
  {
   "name": "Trainwreck: The Real Project X อภิมหาวายป่วง: คืนซ่าส์ปาร์ตี้หลุดโลกของจริง (2025)",
   "info": "พากย์ไทย",
   "image": "https://img.fw4free.com/postor/20250708143245nzRBb18cGBt7V4gqCgiTFXQsGwY.jpg",
   "subtitle": "https://pastebin.com/raw/XjDpyhzb",
   "url": "https://m1free.inwstream.com:1936/movie4/Trainwreck_The_Real_Project_X_2025/Trainwreck_The_Real_Project_X_2025_TH_1080p.mp4/playlist.m3u8",
   "referer": "https://fw4free.com/"
  },
  {
   "name": "Trainwreck: The Real Project X อภิมหาวายป่วง: คืนซ่าส์ปาร์ตี้หลุดโลกของจริง (2025)",
   "info": "บรรยายไทย",
   "image": "https://img.fw4free.com/postor/20250708143245nzRBb18cGBt7V4gqCgiTFXQsGwY.jpg",
   "subtitle": "https://pastebin.com/raw/XjDpyhzb",
   "url": "https://m1free.inwstream.com:1936/movie4/Trainwreck_The_Real_Project_X_2025/Trainwreck_The_Real_Project_X_2025_EN_1080p.mp4/playlist.m3u8",
   "referer": "https://fw4free.com/"
  },
  {
   "name": "Emilia Pérez เอมิเลีย เปเรซ (2024)",
   "info": "พากย์ไทย",
   "image": "https://img.fw4free.com/postor/202501251026417seqaCaaXDNUHOx4DqwpoOH8pPa.jpg",
   "subtitle": "https://pastebin.com/raw/XjDpyhzb",
   "url": "https://m1free.inwstream.com:1936/movie4/Emilia_Perez_2024/Emilia_Perez_2024_TH_1080p.mp4/playlist.m3u8",
   "referer": "https://fw4free.com/"
  },
  {
   "name": "Emilia Pérez เอมิเลีย เปเรซ (2024)",
   "info": "บรรยายไทย",
   "image": "https://img.fw4free.com/postor/202501251026417seqaCaaXDNUHOx4DqwpoOH8pPa.jpg",
   "subtitle": "https://pastebin.com/raw/XjDpyhzb",
   "url": "https://m1free.inwstream.com:1936/movie4/Emilia_Perez_2024/Emilia_Perez_2024_st_1080.mp4/playlist.m3u8",
   "referer": "https://fw4free.com/"
  },
  {
   "name": "On Swift Horses เกมรักซ้อนเงา (2025)",
   "info": "บรรยายไทย",
   "image": "https://img.fw4free.com/postor/20250706214531qs2AeWbLklk9I5UbI8bllZVfF2V.jpg",
   "subtitle": "https://pastebin.com/raw/XjDpyhzb",
   "url": "https://m1free.inwstream.com:1936/movie4/On_Swift_Horses_2024/On_Swift_Horses_2024_st_1080.mp4/playlist.m3u8",
   "referer": "https://fw4free.com/"
  },
  {
   "name": "K-PAX (2001)",
   "info": "พากย์ไทย",
   "image": "https://img.fw4free.com/postor/20250706212609tafXZX0I6rso7EyoEzfygfTqxq6.jpg",
   "subtitle": "https://pastebin.com/raw/XjDpyhzb",
   "url": "https://m1free.inwstream.com:1936/movie4/K_PAX_2001/K_PAX_2001_th_1080.mp4/playlist.m3u8",
   "referer": "https://fw4free.com/"
  },
  {
   "name": "The Final ขอสังหารให้สาสม (2010)",
   "info": "พากย์ไทย",
   "image": "https://img.fw4free.com/postor/202507062120323RU5zKMisCYvkMw2ruTmq1XHJkg.jpg",
   "subtitle": "https://pastebin.com/raw/XjDpyhzb",
   "url": "https://m1free.inwstream.com:1936/movie3/The_Final_2010/The_Final_2010_th_1080_AI.mp4/playlist.m3u8",
   "referer": "https://fw4free.com/"
  },
  {
   "name": "The Final ขอสังหารให้สาสม (2010)",
   "info": "บรรยายไทย",
   "image": "https://img.fw4free.com/postor/202507062120323RU5zKMisCYvkMw2ruTmq1XHJkg.jpg",
   "subtitle": "https://pastebin.com/raw/XjDpyhzb",
   "url": "https://m1free.inwstream.com:1936/movie3/The_Final_2010/The_Final_2010_st_1080_AI.mp4/playlist.m3u8",
   "referer": "https://fw4free.com/"
  },
  {
   "name": "High Rollers แผนปล้นคนหักเหลี่ยม: ทะลวงกาสิโนเดือด (2025)",
   "info": "พากย์ไทย",
   "image": "https://img.fw4free.com/postor/20250706095433hHowAaChDjwueySmwVbsjHmpWa.jpg",
   "subtitle": "https://pastebin.com/raw/XjDpyhzb",
   "url": "https://m1free.inwstream.com:1936/movie4/High_Rollers_2025/High_Rollers_2025_TH_1080p_2.mp4/playlist.m3u8",
   "referer": "https://fw4free.com/"
  },
  {
   "name": "High Rollers แผนปล้นคนหักเหลี่ยม: ทะลวงกาสิโนเดือด (2025)",
   "info": "บรรยายไทย",
   "image": "https://img.fw4free.com/postor/20250706095433hHowAaChDjwueySmwVbsjHmpWa.jpg",
   "subtitle": "https://pastebin.com/raw/XjDpyhzb",
   "url": "https://m1free.inwstream.com:1936/movie4/High_Rollers_2025/High_Rollers_2025_EN_1080p.mp4/playlist.m3u8",
   "referer": "https://fw4free.com/"
  },
  {
   "name": "Martha Marcy May Marlene มาร์ธา ฝ่าโหด หนีอำมหิต (2011)",
   "info": "บรรยายไทย",
   "image": "https://img.fw4free.com/postor/20250705101347eJaO3jdp4VAmpGI7PnqxkmSN1ji.jpg",
   "subtitle": "https://pastebin.com/raw/XjDpyhzb",
   "url": "https://m1free.inwstream.com:1936/movie4/Martha_Marcy_May_Marlene_2011/Martha_Marcy_May_Marlene_2011_EN_1080p.mp4/playlist.m3u8",
   "referer": "https://fw4free.com/"
  },
  {
   "name": "Gia เจีย (1998)",
   "info": "บรรยายไทย",
   "image": "https://img.fw4free.com/postor/20250705091632oFi5OIvBf59W1KFaN0cuiMEEbs1.jpg",
   "subtitle": "https://pastebin.com/raw/XjDpyhzb",
   "url": "https://m1free.inwstream.com:1936/movie4/Gia.1998/Gia.1998_EN_1080p.mp4/playlist.m3u8",
   "referer": "https://fw4free.com/"
  },
  {
   "name": "Black Water: Abyss กระชากนรก โคตรไอ้เข้ (2020)",
   "info": "พากย์ไทย",
   "image": "https://img.fw4free.com/postor/2025070415581395S6PinQIvVe4uJAd82a2iGZ0rA.jpg",
   "subtitle": "https://pastebin.com/raw/XjDpyhzb",
   "url": "https://m1free.inwstream.com:1936/movie3/Black_Water_Abyss_2020/Black_Water_Abyss_2020_th_1080.mp4/playlist.m3u8",
   "referer": "https://fw4free.com/"
  },
  {
   "name": "Black Water: Abyss กระชากนรก โคตรไอ้เข้ (2020)",
   "info": "บรรยายไทย",
   "image": "https://img.fw4free.com/postor/2025070415581395S6PinQIvVe4uJAd82a2iGZ0rA.jpg",
   "subtitle": "https://pastebin.com/raw/XjDpyhzb",
   "url": "https://m1free.inwstream.com:1936/movie3/Black_Water_Abyss_2020/Black_Water_Abyss_2020_st_1080_T.mp4/playlist.m3u8",
   "referer": "https://fw4free.com/"
  },
  {
   "name": "Heads of State ผู้นำสายบู๊กู้วิกฤต (2025)",
   "info": "พากย์ไทย",
   "image": "https://img.fw4free.com/postor/202507030820041CfBzb8xDIkSlxlwyo005lXpoAX.jpg",
   "subtitle": "https://pastebin.com/raw/XjDpyhzb",
   "url": "https://m1free.inwstream.com:1936/movie4/Heads_of_State_2025/Heads_of_State_2025_TH_1080p.mp4/playlist.m3u8",
   "referer": "https://fw4free.com/"
  },
  {
   "name": "Heads of State ผู้นำสายบู๊กู้วิกฤต (2025)",
   "info": "บรรยายไทย",
   "image": "https://img.fw4free.com/postor/202507030820041CfBzb8xDIkSlxlwyo005lXpoAX.jpg",
   "subtitle": "https://pastebin.com/raw/XjDpyhzb",
   "url": "https://m1free.inwstream.com:1936/movie4/Heads_of_State_2025/Heads_of_State_2025_EN_1080p.mp4/playlist.m3u8",
   "referer": "https://fw4free.com/"
  },
  {
   "name": "The Old Guard 2 ดิ โอลด์ การ์ด 2 (2025)",
   "info": "พากย์ไทย",
   "image": "https://img.fw4free.com/postor/202507021457492Kflmz9Qt5UQ97JtU8mn6wTrr0z.jpg",
   "subtitle": "https://pastebin.com/raw/XjDpyhzb",
   "url": "https://m1free.inwstream.com:1936/movie4/The_Old_Guard_2_2025/The_Old_Guard_2_2025_TH_1080p.mp4/playlist.m3u8",
   "referer": "https://fw4free.com/"
  },
  {
   "name": "The Old Guard 2 ดิ โอลด์ การ์ด 2 (2025)",
   "info": "บรรยายไทย",
   "image": "https://img.fw4free.com/postor/202507021457492Kflmz9Qt5UQ97JtU8mn6wTrr0z.jpg",
   "subtitle": "https://pastebin.com/raw/XjDpyhzb",
   "url": "https://m1free.inwstream.com:1936/movie4/The_Old_Guard_2_2025/The_Old_Guard_2_2025_EN_1080p.mp4/playlist.m3u8",
   "referer": "https://fw4free.com/"
  },
  {
   "name": "Trainwreck: The Cult of American Apparel อภิมหาวายป่วง: ลัทธิอเมริกันแอพพาเรล (2025)",
   "info": "พากย์ไทย",
   "image": "https://img.fw4free.com/postor/20250702065322vZBoQrjl34rOwfZaoj5IF8ylGSF.jpg",
   "subtitle": "https://pastebin.com/raw/XjDpyhzb",
   "url": "https://m1free.inwstream.com:1936/movie4/Trainwreck_The_Cult_of_American_Apparel_2025/Trainwreck_The_Cult_of_American_Apparel_2025_TH_1080p.mp4/playlist.m3u8",
   "referer": "https://fw4free.com/"
  },
  {
   "name": "Trainwreck: The Cult of American Apparel อภิมหาวายป่วง: ลัทธิอเมริกันแอพพาเรล (2025)",
   "info": "บรรยายไทย",
   "image": "https://img.fw4free.com/postor/20250702065322vZBoQrjl34rOwfZaoj5IF8ylGSF.jpg",
   "subtitle": "https://pastebin.com/raw/XjDpyhzb",
   "url": "https://m1free.inwstream.com:1936/movie4/Trainwreck_The_Cult_of_American_Apparel_2025/Trainwreck_The_Cult_of_American_Apparel_2025_EN_1080p.mp4/playlist.m3u8",
   "referer": "https://fw4free.com/"
  },
  {
   "name": "Bono: Stories of Surrender (2025)",
   "info": "บรรยายไทย",
   "image": "https://img.fw4free.com/postor/20250701180439ctofSj5nMQDtB1q9TdIQx30P3bY.jpg",
   "subtitle": "https://pastebin.com/raw/XjDpyhzb",
   "url": "https://m1free.inwstream.com:1936/movie4/Bono_Stories_of_Surrender_2025/Bono_Stories_of_Surrender_2025_st_1080.mp4/playlist.m3u8",
   "referer": "https://fw4free.com/"
  },
  {
   "name": "Shark Whisperer คนรักษ์ฉลาม (2025)",
   "info": "พากย์ไทย",
   "image": "https://img.fw4free.com/postor/20250701080512or7Y0eL9OBxFoACnW9FdTLpaDFp.jpg",
   "subtitle": "https://pastebin.com/raw/XjDpyhzb",
   "url": "https://m1free.inwstream.com:1936/movie4/Shark_Whisperer_2025/Shark_Whisperer_2025_TH_1080p.mp4/playlist.m3u8",
   "referer": "https://fw4free.com/"
  },
  {
   "name": "Shark Whisperer คนรักษ์ฉลาม (2025)",
   "info": "บรรยายไทย",
   "image": "https://img.fw4free.com/postor/20250701080512or7Y0eL9OBxFoACnW9FdTLpaDFp.jpg",
   "subtitle": "https://pastebin.com/raw/XjDpyhzb",
   "url": "https://m1free.inwstream.com:1936/movie4/Shark_Whisperer_2025/Shark_Whisperer_2025_EN_1080p.mp4/playlist.m3u8",
   "referer": "https://fw4free.com/"
  },
    {
        "name": "Something in the Water ครีบขย้ำคลั่งมหาสมุทร (2024)",
        "info": "พากย์ไทย",
        "image": "https://img.fw4free.com/postor/202406111720341iWGGxHEwswZGvPSoMZlLFf0PNq.jpg",
        "subtitle": "https://pastebin.com/raw/XjDpyhzb",
        "url": "https://m1free.inwstream.com:1936/movie4/Something_in_the_Water_2024/Something_in_the_Water_2024_TH_1080p.mp4/playlist.m3u8",
        "referer": "https://fw4free.com/"
    },
    {
        "name": "Something in the Water ครีบขย้ำคลั่งมหาสมุทร (2024)",
        "info": "บรรยายไทย",
        "image": "https://img.fw4free.com/postor/202406111720341iWGGxHEwswZGvPSoMZlLFf0PNq.jpg",
        "subtitle": "https://pastebin.com/raw/XjDpyhzb",
        "url": "https://m1free.inwstream.com:1936/movie4/Something_in_the_Water_2024/Something_in_the_Water_2024_EN_1080p.mp4/playlist.m3u8",
        "referer": "https://fw4free.com/"
    },
    {
        "name": "Clown in a Cornfield คืนวิปลาสแห่งเคตเทิลสปริงส์ (2025)",
        "info": "บรรยายไทย",
        "image": "https://img.fw4free.com/postor/202506290951386ep6gw90TJ8bYvJC6hEDo8SxjoJ.jpg",
        "subtitle": "https://pastebin.com/raw/XjDpyhzb",
        "url": "https://m1free.inwstream.com:1936/movie4/Clown_in_a_Cornfield_2025/Clown_in_a_Cornfield_2025_EN_1080p.mp4/playlist.m3u8",
        "referer": "https://fw4free.com/"
    },
    {
        "name": "Nosferatu นอสเฟอราตู (2024)",
        "info": "พากย์ไทย",
        "image": "https://img.fw4free.com/postor/20250222212326bh6EPgbukuapRC76adlIss5Dom7.jpg",
        "subtitle": "https://pastebin.com/raw/XjDpyhzb",
        "url": "https://m1free.inwstream.com:1936/movie4/Nosferatu_2024/Nosferatu_2024_TH_1080p.mp4/playlist.m3u8",
        "referer": "https://fw4free.com/"
    },
    {
        "name": "Nosferatu นอสเฟอราตู (2024)",
        "info": "บรรยายไทย",
        "image": "https://img.fw4free.com/postor/20250222212326bh6EPgbukuapRC76adlIss5Dom7.jpg",
        "subtitle": "https://pastebin.com/raw/XjDpyhzb",
        "url": "https://m1free.inwstream.com:1936/movie4/Nosferatu_2024/Nosferatu_2024_st_1080.mp4/playlist.m3u8",
        "referer": "https://fw4free.com/"
    },
    {
        "name": "Falling in Love รักแท้ นิรันดร์ (1984)",
        "info": "บรรยายไทย",
        "image": "https://img.fw4free.com/postor/20250627095743c8Ti4tOwAmY6RhUxV9JsXl2W4l7.jpg",
        "subtitle": "https://pastebin.com/raw/XjDpyhzb",
        "url": "https://m1free.inwstream.com:1936/movie4/Falling_in_Love_1984/Falling_in_Love_1984_EN_1080p.mp4/playlist.m3u8",
        "referer": "https://fw4free.com/"
    },
    {
        "name": "Summer of 69 (2025)",
        "info": "บรรยายไทย",
        "image": "https://img.fw4free.com/postor/20250626104635xBmsHHLwvwI29oyFE48fKAnSQyk.jpg",
        "subtitle": "https://pastebin.com/raw/XjDpyhzb",
        "url": "https://m1free.inwstream.com:1936/movie4/Summer_of_69_2025/Summer_of_69_2025_EN_1080p_1.mp4/playlist.m3u8",
        "referer": "https://fw4free.com/"
    },
    {
        "name": "I'm Your Venus ฉันคือวีนัส (2024)",
        "info": "บรรยายไทย",
        "image": "https://img.fw4free.com/postor/20250625083919dzvEPrSJGyVAdUdOBzVniym3XQI.jpg",
        "subtitle": "https://pastebin.com/raw/XjDpyhzb",
        "url": "https://m1free.inwstream.com:1936/movie4/I_m_Your_Venus_2024/I_m_Your_Venus_2024_EN_1080p.mp4/playlist.m3u8",
        "referer": "https://fw4free.com/"
    },
    {
        "name": "The Brutalist เดอะ บรูทัลลิสต์ (2024)",
        "info": "พากย์ไทย",
        "image": "https://img.fw4free.com/postor/20250408143445b0dyZlvVQml1KgQpJQbA5osr5c8.jpg",
        "subtitle": "https://pastebin.com/raw/XjDpyhzb",
        "url": "https://m1free.inwstream.com:1936/movie4/The_Brutalist_2024/The_Brutalist_2024_TH_1080p.mp4/playlist.m3u8",
        "referer": "https://fw4free.com/"
    },
    {
        "name": "The Brutalist เดอะ บรูทัลลิสต์ (2024)",
        "info": "บรรยายไทย",
        "image": "https://img.fw4free.com/postor/20250408143445b0dyZlvVQml1KgQpJQbA5osr5c8.jpg",
        "subtitle": "https://pastebin.com/raw/XjDpyhzb",
        "url": "https://m1free.inwstream.com:1936/movie4/The_Brutalist_2024/The_Brutalist_2024_st_1080.mp4/playlist.m3u8",
        "referer": "https://fw4free.com/"
    },
    {
        "name": "Trainwreck: Poop Cruise อภิมหาวายป่วง: เรือสำราญอุนจิ (2025)",
        "info": "พากย์ไทย",
        "image": "https://img.fw4free.com/postor/20250624180302cyBad0YS15u3rgIGML56F59mPQv.jpg",
        "subtitle": "https://pastebin.com/raw/XjDpyhzb",
        "url": "https://m1free.inwstream.com:1936/movie4/Trainwreck_Poop_Cruise_2025/Trainwreck_Poop_Cruise_2025_TH_1080p.mp4/playlist.m3u8",
        "referer": "https://fw4free.com/"
    },
    {
        "name": "Trainwreck: Poop Cruise อภิมหาวายป่วง: เรือสำราญอุนจิ (2025)",
        "info": "บรรยายไทย",
        "image": "https://img.fw4free.com/postor/20250624180302cyBad0YS15u3rgIGML56F59mPQv.jpg",
        "subtitle": "https://pastebin.com/raw/XjDpyhzb",
        "url": "https://m1free.inwstream.com:1936/movie4/Trainwreck_Poop_Cruise_2025/Trainwreck_Poop_Cruise_2025_EN_1080p.mp4/playlist.m3u8",
        "referer": "https://fw4free.com/"
    },
    {
        "name": "Warfare (2025)",
        "info": "บรรยายไทย",
        "image": "https://img.fw4free.com/postor/20250624090407srj9rYrjefyWqkLc6l2xjTGeBGO.jpg",
        "subtitle": "https://pastebin.com/raw/XjDpyhzb",
        "url": "https://m1free.inwstream.com:1936/movie4/Warfare_2025/Warfare_2025_EN_1080p_T.mp4/playlist.m3u8",
        "referer": "https://fw4free.com/"
    },
    {
        "name": "Late Night with the Devil คืนนี้ผีมาคุย (2023)",
        "info": "พากย์ไทย",
        "image": "https://img.fw4free.com/postor/202506240857425qDbCRHO85UK8IaJDmRVhTzz3IX.jpg",
        "subtitle": "https://pastebin.com/raw/XjDpyhzb",
        "url": "https://m1free.inwstream.com:1936/movie3/Late_Night_with_the_Devil_2023/Late_Night_with_the_Devil_2023_TH_1080p.mp4/playlist.m3u8",
        "referer": "https://fw4free.com/"
    },
    {
        "name": "Late Night with the Devil คืนนี้ผีมาคุย (2023)",
        "info": "บรรยายไทย",
        "image": "https://img.fw4free.com/postor/202506240857425qDbCRHO85UK8IaJDmRVhTzz3IX.jpg",
        "subtitle": "https://pastebin.com/raw/XjDpyhzb",
        "url": "https://m1free.inwstream.com:1936/movie3/Late_Night_with_the_Devil_2023/Late_Night_with_the_Devil_2023_EN_1080p.mp4/playlist.m3u8",
        "referer": "https://fw4free.com/"
    },
    {
        "name": "Miller's Girl หลักสูตรร้อนซ่อนรัก (2024)",
        "info": "พากย์ไทย",
        "image": "https://img.fw4free.com/postor/20250624051550ieU0zUj7WhE0GrgpgofRH0sNjbI.jpg",
        "subtitle": "https://pastebin.com/raw/XjDpyhzb",
        "url": "https://m1free.inwstream.com:1936/movie4/Miller_s_Girl_2024/Miller_s_Girl_2024_th_1080.mp4/playlist.m3u8",
        "referer": "https://fw4free.com/"
    },
    {
        "name": "Miller's Girl หลักสูตรร้อนซ่อนรัก (2024)",
        "info": "บรรยายไทย",
        "image": "https://img.fw4free.com/postor/20250624051550ieU0zUj7WhE0GrgpgofRH0sNjbI.jpg",
        "subtitle": "https://pastebin.com/raw/XjDpyhzb",
        "url": "https://m1free.inwstream.com:1936/movie4/Miller_s_Girl_2024/Miller_s_Girl_2024_st_1080.mp4/playlist.m3u8",
        "referer": "https://fw4free.com/"
    },
    {
        "name": "Kraken คราเคน เลื้อยสยอง 20,000 โยชน์ (2025)",
        "info": "พากย์ไทย",
        "image": "https://img.fw4free.com/postor/20250621042408xpvXJtizCp0WuvgiV1hj3WgJZJf.jpg",
        "subtitle": "https://pastebin.com/raw/XjDpyhzb",
        "url": "https://m1free.inwstream.com:1936/movie4/Kraken_2025/Kraken_2025_th_1080_1.mp4/playlist.m3u8",
        "referer": "https://fw4free.com/"
    },
    {
        "name": "Kraken คราเคน เลื้อยสยอง 20,000 โยชน์ (2025)",
        "info": "บรรยายไทย",
        "image": "https://img.fw4free.com/postor/20250621042408xpvXJtizCp0WuvgiV1hj3WgJZJf.jpg",
        "subtitle": "https://pastebin.com/raw/XjDpyhzb",
        "url": "https://m1free.inwstream.com:1936/movie4/Kraken_2025/Kraken_2025_st_1080.mp4/playlist.m3u8",
        "referer": "https://fw4free.com/"
    },
    {
        "name": "Faust: Love of the Damned พันธุ์นรกครึ่งคน (2000)",
        "info": "พากย์ไทย",
        "image": "https://img.fw4free.com/postor/20250621042047yvmvjTInRSUJECmO462r5GbSMlH.jpg",
        "subtitle": "https://pastebin.com/raw/XjDpyhzb",
        "url": "https://m1free.inwstream.com:1936/movie4/Faust_Love_of_the_Damned_2000/Faust_Love_of_the_Damned_2000_th_1080.mp4/playlist.m3u8",
        "referer": "https://fw4free.com/"
    },
    {
        "name": "Faust: Love of the Damned พันธุ์นรกครึ่งคน (2000)",
        "info": "บรรยายไทย",
        "image": "https://img.fw4free.com/postor/20250621042047yvmvjTInRSUJECmO462r5GbSMlH.jpg",
        "subtitle": "https://pastebin.com/raw/XjDpyhzb",
        "url": "https://m1free.inwstream.com:1936/movie4/Faust_Love_of_the_Damned_2000/Faust_Love_of_the_Damned_2000_st_1080.mp4/playlist.m3u8",
        "referer": "https://fw4free.com/"
    },
    {
        "name": "Frozen: The Hit Broadway Musical (2025)",
        "info": "บรรยายไทย",
        "image": "https://img.fw4free.com/postor/2025062104073540scWHddXAuX2CL7CJOn5hUrdyQ.jpg",
        "subtitle": "https://pastebin.com/raw/XjDpyhzb",
        "url": "https://m1free.inwstream.com:1936/movie4/Frozen_The_Hit_Broadway_Musical_2025/Frozen_The_Hit_Broadway_Musical_2025_st_1080.mp4/playlist.m3u8",
        "referer": "https://fw4free.com/"
    },
    {
        "name": "Grenfell: Uncovered ค้นความจริงเหตุเพลิงไหม้เกรนเฟลล์ ทาวเวอร์ (2025)",
        "info": "บรรยายไทย",
        "image": "https://img.fw4free.com/postor/20250620154616MV5BNmI1NzI3ZWMtMGM0MC00NmE0LTk1YTgtMjk3MGU2OWRlZGQ0XkEyXkFqcGc@._V1_FMjpg_UX1000_.jpg",
        "subtitle": "https://pastebin.com/raw/XjDpyhzb",
        "url": "https://m1free.inwstream.com:1936/movie4/Grenfell_Uncovered_2025/Grenfell_Uncovered_2025_EN_1080p.mp4/playlist.m3u8",
        "referer": "https://fw4free.com/"
    },
    {
        "name": "Semi-Soeter เรื่องรักกึ่งหวาน งานนี้บานปลาย (2025)",
        "info": "บรรยายไทย",
        "image": "https://img.fw4free.com/postor/20250620152303xTJXvW3u16MwMwGYnG1k2R96zYS.jpg",
        "subtitle": "https://pastebin.com/raw/XjDpyhzb",
        "url": "https://m1free.inwstream.com:1936/movie4/Semi_Soeter_2025/Semi_Soeter_2025_ST_1080p.mp4/playlist.m3u8",
        "referer": "https://fw4free.com/"
    },
    {
        "name": "A King Like Me ราชาอย่างฉัน (2024)",
        "info": "บรรยายไทย",
        "image": "https://img.fw4free.com/postor/20250620090243dr9ouxc6vP7oF6loXKc9dISuezQ.jpg",
        "subtitle": "https://pastebin.com/raw/XjDpyhzb",
        "url": "https://m1free.inwstream.com:1936/movie4/A_King_Like_Me_2024/A_King_Like_Me_2024_EN_1080p.mp4/playlist.m3u8",
        "referer": "https://fw4free.com/"
    },
    {
        "name": "Final Destination Bloodlines ไฟนอล เดสติเนชั่น ทายาทโกงตาย (2025)",
        "info": "พากย์ไทย",
        "image": "https://img.fw4free.com/postor/202505222129306WxhEvFsauuACfv8HyoVX6mZKFj.jpg",
        "subtitle": "https://pastebin.com/raw/XjDpyhzb",
        "url": "https://m1free.inwstream.com:1936/movie4/Final_Destination_Bloodlines_2025/Final_Destination_Bloodlines_2025_th_1080.mp4/playlist.m3u8",
        "referer": "https://fw4free.com/"
    },
    {
        "name": "Final Destination Bloodlines ไฟนอล เดสติเนชั่น ทายาทโกงตาย (2025)",
        "info": "บรรยายไทย",
        "image": "https://img.fw4free.com/postor/202505222129306WxhEvFsauuACfv8HyoVX6mZKFj.jpg",
        "subtitle": "https://pastebin.com/raw/XjDpyhzb",
        "url": "https://m1free.inwstream.com:1936/movie4/Final_Destination_Bloodlines_2025/Final_Destination_Bloodlines_2025_st_1080.mp4/playlist.m3u8",
        "referer": "https://fw4free.com/"
    },
    {
        "name": "Trainwreck: Mayor of Mayhem อภิมหาวายป่วง: นายกเทศมนตรีแห่งความโกลาหล (2025)",
        "info": "พากย์ไทย",
        "image": "https://img.fw4free.com/postor/202506180830252IA1Q16FBDhMkvpBsHaihtx6c31.jpg",
        "subtitle": "https://pastebin.com/raw/XjDpyhzb",
        "url": "https://m1free.inwstream.com:1936/movie4/Trainwreck_Mayor_of_Mayhem_2025/Trainwreck_Mayor_of_Mayhem_2025_TH_1080p.mp4/playlist.m3u8",
        "referer": "https://fw4free.com/"
    },
    {
        "name": "Trainwreck: Mayor of Mayhem อภิมหาวายป่วง: นายกเทศมนตรีแห่งความโกลาหล (2025)",
        "info": "บรรยายไทย",
        "image": "https://img.fw4free.com/postor/202506180830252IA1Q16FBDhMkvpBsHaihtx6c31.jpg",
        "subtitle": "https://pastebin.com/raw/XjDpyhzb",
        "url": "https://m1free.inwstream.com:1936/movie4/Trainwreck_Mayor_of_Mayhem_2025/Trainwreck_Mayor_of_Mayhem_2025_EN_1080p.mp4/playlist.m3u8",
        "referer": "https://fw4free.com/"
    },
    {
        "name": "Latin Blood - The Ballad of Ney Matogrosso (Homem com H)",
        "info": "บรรยายไทย",
        "image": "https://img.fw4free.com/postor/20250618082532aY6RUi2npX3yUBLQulAuxgoVegs.jpg",
        "subtitle": "https://pastebin.com/raw/XjDpyhzb",
        "url": "https://m1free.inwstream.com:1936/movie4/Latin_Blood_The_Ballad_of_Ney_Matogrosso_2025/Latin_Blood_The_Ballad_of_Ney_Matogrosso_2025_ST_1080p.mp4/playlist.m3u8",
        "referer": "https://fw4free.com/"
    },
    {
        "name": "Scary Movie 5 ยำหนังจี้ เรียลลิตี้หลุดโลก (2013)",
        "info": "พากย์ไทย",
        "image": "https://img.fw4free.com/postor/202506172118109WNozxN2UVf7rA73FJBWdWJZhfP.jpg",
        "subtitle": "https://pastebin.com/raw/XjDpyhzb",
        "url": "https://m1free.inwstream.com:1936/movie4/Scary_Movie_5_2013/Scary_Movie_5_2013_th_1080.mp4/playlist.m3u8",
        "referer": "https://fw4free.com/"
    },
    {
        "name": "Scary Movie 5 ยำหนังจี้ เรียลลิตี้หลุดโลก (2013)",
        "info": "บรรยายไทย",
        "image": "https://img.fw4free.com/postor/202506172118109WNozxN2UVf7rA73FJBWdWJZhfP.jpg",
        "subtitle": "https://pastebin.com/raw/XjDpyhzb",
        "url": "https://m1free.inwstream.com:1936/movie4/Scary_Movie_5_2013/Scary_Movie_5_2013_st_1080.mp4/playlist.m3u8",
        "referer": "https://fw4free.com/"
    },
    {
        "name": "Scary Movie 4 ยำหนังจี้ หวีดล้างโลก (2006)",
        "info": "พากย์ไทย",
        "image": "https://img.fw4free.com/postor/20250617211303vL03Mk1ES5uo1ZdXovz6NtgsbSb.jpg",
        "subtitle": "https://pastebin.com/raw/XjDpyhzb",
        "url": "https://m1free.inwstream.com:1936/movie4/Scary_Movie_4_2006/Scary_Movie_4_2006_th_1080.mp4/playlist.m3u8",
        "referer": "https://fw4free.com/"
    },
    {
        "name": "Scary Movie 4 ยำหนังจี้ หวีดล้างโลก (2006)",
        "info": "บรรยายไทย",
        "image": "https://img.fw4free.com/postor/20250617211303vL03Mk1ES5uo1ZdXovz6NtgsbSb.jpg",
        "subtitle": "https://pastebin.com/raw/XjDpyhzb",
        "url": "https://m1free.inwstream.com:1936/movie4/Scary_Movie_4_2006/Scary_Movie_4_2006_st_1080.mp4/playlist.m3u8",
        "referer": "https://fw4free.com/"
    },
    {
        "name": "Scary Movie 3 สยองหวีดจี้ ดีจังหว่า (2003)",
        "info": "พากย์ไทย",
        "image": "https://img.fw4free.com/postor/20250617210426A6t3OUc1PSb7Tyvsinh9vJA1HlL.jpg",
        "subtitle": "https://pastebin.com/raw/XjDpyhzb",
        "url": "https://m1free.inwstream.com:1936/movie4/Scary_Movie_3_2003/Scary_Movie_3_2003_th_1080.mp4/playlist.m3u8",
        "referer": "https://fw4free.com/"
    },
    {
        "name": "Scary Movie 3 สยองหวีดจี้ ดีจังหว่า (2003)",
        "info": "บรรยายไทย",
        "image": "https://img.fw4free.com/postor/20250617210426A6t3OUc1PSb7Tyvsinh9vJA1HlL.jpg",
        "subtitle": "https://pastebin.com/raw/XjDpyhzb",
        "url": "https://m1free.inwstream.com:1936/movie4/Scary_Movie_3_2003/Scary_Movie_3_2003_st_1080.mp4/playlist.m3u8",
        "referer": "https://fw4free.com/"
    },
    {
        "name": "Scary Movie 2 หวีด(อีกสักที)",
        "info": "พากย์ไทย",
        "image": "https://img.fw4free.com/postor/202506172058597Eb1JWK0Cb0rbfsYjwfc9g0PbQH.jpg",
        "subtitle": "https://pastebin.com/raw/XjDpyhzb",
        "url": "https://m1free.inwstream.com:1936/movie4/Scary_Movie_2_2001/Scary_Movie_2_2001_th_1080.mp4/playlist.m3u8",
        "referer": "https://fw4free.com/"
    },
    {
        "name": "Scary Movie 2 หวีด(อีกสักที)",
        "info": "บรรยายไทย",
        "image": "https://img.fw4free.com/postor/202506172058597Eb1JWK0Cb0rbfsYjwfc9g0PbQH.jpg",
        "subtitle": "https://pastebin.com/raw/XjDpyhzb",
        "url": "https://m1free.inwstream.com:1936/movie4/Scary_Movie_2_2001/Scary_Movie_2_2001_st_1080.mp4/playlist.m3u8",
        "referer": "https://fw4free.com/"
    },
    {
        "name": "Scary Movie ยำหนังจี้​ หวีดดีไหมหว่า? (2000)",
        "info": "พากย์ไทย",
        "image": "https://img.fw4free.com/postor/202506172050412HWf4Z7zUqg5QtXow0IoS2ci7X9.jpg",
        "subtitle": "https://pastebin.com/raw/XjDpyhzb",
        "url": "https://m1free.inwstream.com:1936/movie4/Scary_Movie_2000/Scary_Movie_2000_th_1080.mp4/playlist.m3u8",
        "referer": "https://fw4free.com/"
    },
    {
        "name": "Scary Movie ยำหนังจี้​ หวีดดีไหมหว่า? (2000)",
        "info": "บรรยายไทย",
        "image": "https://img.fw4free.com/postor/202506172050412HWf4Z7zUqg5QtXow0IoS2ci7X9.jpg",
        "subtitle": "https://pastebin.com/raw/XjDpyhzb",
        "url": "https://m1free.inwstream.com:1936/movie4/Scary_Movie_2000/Scary_Movie_2000_st_1080.mp4/playlist.m3u8",
        "referer": "https://fw4free.com/"
    },
    {
        "name": "Studio 666 (2022)",
        "info": "พากย์ไทย",
        "image": "https://img.fw4free.com/postor/20220428042846zD2XyaV6eGEEgEzVnjg0hQVR5yz.jpg",
        "subtitle": "https://pastebin.com/raw/XjDpyhzb",
        "url": "https://m1free.inwstream.com:1936/movie3/Studio_666_2022/Studio_666_2022_TH_1080p.mp4/playlist.m3u8",
        "referer": "https://fw4free.com/"
    },
    {
        "name": "Studio 666 (2022)",
        "info": "บรรยายไทย",
        "image": "https://img.fw4free.com/postor/20220428042846zD2XyaV6eGEEgEzVnjg0hQVR5yz.jpg",
        "subtitle": "https://pastebin.com/raw/XjDpyhzb",
        "url": "https://m1free.inwstream.com:1936/movie3/Studio_666_2022/Studio_666_2022_en_5_1_1080p.mp4/playlist.m3u8",
        "referer": "https://fw4free.com/"
    },
    {
        "name": "The Exorcism ดิ เอ็กซอร์ซิสม์ นรก สิง สาป (2024)",
        "info": "พากย์ไทย",
        "image": "https://img.fw4free.com/postor/20250616121457v4PgVcOne2sumkyOK8O7BKB9PWX.jpg",
        "subtitle": "https://pastebin.com/raw/XjDpyhzb",
        "url": "https://m1free.inwstream.com:1936/movie4/The_Exorcism_2024/The_Exorcism_2024_TH_1080p.mp4/playlist.m3u8",
        "referer": "https://fw4free.com/"
    },
    {
        "name": "The Exorcism ดิ เอ็กซอร์ซิสม์ นรก สิง สาป (2024)",
        "info": "บรรยายไทย",
        "image": "https://img.fw4free.com/postor/20250616121457v4PgVcOne2sumkyOK8O7BKB9PWX.jpg",
        "subtitle": "https://pastebin.com/raw/XjDpyhzb",
        "url": "https://m1free.inwstream.com:1936/movie4/The_Exorcism_2024/The_Exorcism_2024_EN_1080p.mp4/playlist.m3u8",
        "referer": "https://fw4free.com/"
    },
    {
        "name": "The Experiment คุกทมิฬ (2010)",
        "info": "พากย์ไทย",
        "image": "https://img.fw4free.com/postor/20250615230403zy6hJYii2PJfMRoUBlULhfuLsgL.jpg",
        "subtitle": "https://pastebin.com/raw/XjDpyhzb",
        "url": "https://m1free.inwstream.com:1936/movie4/The_Experiment_2010/The_Experiment_2010_th_1080.mp4/playlist.m3u8",
        "referer": "https://fw4free.com/"
    },
    {
        "name": "The Experiment คุกทมิฬ (2010)",
        "info": "บรรยายไทย",
        "image": "https://img.fw4free.com/postor/20250615230403zy6hJYii2PJfMRoUBlULhfuLsgL.jpg",
        "subtitle": "https://pastebin.com/raw/XjDpyhzb",
        "url": "https://m1free.inwstream.com:1936/movie4/The_Experiment_2010/The_Experiment_2010_st_1080.mp4/playlist.m3u8",
        "referer": "https://fw4free.com/"
    },
    {
        "name": "Dirty Angels นางฟ้าพันธุ์ดุ (2024)",
        "info": "พากย์ไทย",
        "image": "https://img.fw4free.com/postor/202503282047443O3qSGmjRGc10hMwFul8WDxKE5t.jpg",
        "subtitle": "https://pastebin.com/raw/XjDpyhzb",
        "url": "https://m1free.inwstream.com:1936/movie4/Dirty_Angels_2024/Dirty_Angels_2024_th_1080.mp4/playlist.m3u8",
        "referer": "https://fw4free.com/"
    },
    {
        "name": "Dirty Angels นางฟ้าพันธุ์ดุ (2024)",
        "info": "บรรยายไทย",
        "image": "https://img.fw4free.com/postor/202503282047443O3qSGmjRGc10hMwFul8WDxKE5t.jpg",
        "subtitle": "https://pastebin.com/raw/XjDpyhzb",
        "url": "https://m1free.inwstream.com:1936/movie4/Dirty_Angels_2024/Dirty_Angels_2024_st_1080.mp4/playlist.m3u8",
        "referer": "https://fw4free.com/"
    },
    {
        "name": "Hostel นรกรอชำแหละ (2005)",
        "info": "พากย์ไทย",
        "image": "https://img.fw4free.com/postor/20250614193148tzrqbj6nj4ylDVjrcUcoAmFyzvE.jpg",
        "subtitle": "https://pastebin.com/raw/XjDpyhzb",
        "url": "https://m1free.inwstream.com:1936/movie4/Hostel_2005/Hostel_2005_th_1080.mp4/playlist.m3u8",
        "referer": "https://fw4free.com/"
    },
    {
        "name": "Hostel นรกรอชำแหละ (2005)",
        "info": "บรรยายไทย",
        "image": "https://img.fw4free.com/postor/20250614193148tzrqbj6nj4ylDVjrcUcoAmFyzvE.jpg",
        "subtitle": "https://pastebin.com/raw/XjDpyhzb",
        "url": "https://m1free.inwstream.com:1936/movie4/Hostel_2005/Hostel_2005_st_1080.mp4/playlist.m3u8",
        "referer": "https://fw4free.com/"
    },
    {
        "name": "Echo Valley (2025)",
        "info": "บรรยายไทย",
        "image": "https://img.fw4free.com/postor/202506140854373Ey3HuqZdrx1rfxRkfiOXDFtvtl.jpg",
        "subtitle": "https://pastebin.com/raw/XjDpyhzb",
        "url": "https://m1free.inwstream.com:1936/movie4/Echo_Valley_2025/Echo_Valley_2025_EN_1080p.mp4/playlist.m3u8",
        "referer": "https://fw4free.com/"
    },
    {
        "name": "Deep Cover ภารกิจด้นสด ปลดล็อกสกิลรั่ว (2025)",
        "info": "พากย์ไทย",
        "image": "https://img.fw4free.com/postor/202506130859001vXTHTbSQJs9r2hp4Uk08XzKwPp.jpg",
        "subtitle": "https://pastebin.com/raw/XjDpyhzb",
        "url": "https://m1free.inwstream.com:1936/movie4/Deep_Cover_2025/Deep_Cover_2025_TH_1080p.mp4/playlist.m3u8",
        "referer": "https://fw4free.com/"
    },
    {
        "name": "Deep Cover ภารกิจด้นสด ปลดล็อกสกิลรั่ว (2025)",
        "info": "บรรยายไทย",
        "image": "https://img.fw4free.com/postor/202506130859001vXTHTbSQJs9r2hp4Uk08XzKwPp.jpg",
        "subtitle": "https://pastebin.com/raw/XjDpyhzb",
        "url": "https://m1free.inwstream.com:1936/movie4/Deep_Cover_2025/Deep_Cover_2025_EN_1080p.mp4/playlist.m3u8",
        "referer": "https://fw4free.com/"
    },
    {
        "name": "Hostel: Part III นรกรอชำแหละ 3 (2011)",
        "info": "พากย์ไทย",
        "image": "https://img.fw4free.com/postor/20250612180629ieO49ludO6DxRVV8u1LKMjtrDLN.jpg",
        "subtitle": "https://pastebin.com/raw/XjDpyhzb",
        "url": "https://m1free.inwstream.com:1936/movie4/Hostel_Part_III_2011/Hostel_Part_III_2011_th_1080.mp4/playlist.m3u8",
        "referer": "https://fw4free.com/"
    },
    {
        "name": "Hostel: Part III นรกรอชำแหละ 3 (2011)",
        "info": "บรรยายไทย",
        "image": "https://img.fw4free.com/postor/20250612180629ieO49ludO6DxRVV8u1LKMjtrDLN.jpg",
        "subtitle": "https://pastebin.com/raw/XjDpyhzb",
        "url": "https://m1free.inwstream.com:1936/movie4/Hostel_Part_III_2011/Hostel_Part_III_2011_st_1080.mp4/playlist.m3u8",
        "referer": "https://fw4free.com/"
    },
    {
        "name": "Hostel: Part II นรกรอชำแหละ 2 (2007)",
        "info": "พากย์ไทย",
        "image": "https://img.fw4free.com/postor/20250612180125vKzW1zixWWwvmPipevcetxsCmKA.jpg",
        "subtitle": "https://pastebin.com/raw/XjDpyhzb",
        "url": "https://m1free.inwstream.com:1936/movie4/Hostel_Part_II_2007/Hostel_Part_II_2007_th_1080.mp4/playlist.m3u8",
        "referer": "https://fw4free.com/"
    },
    {
        "name": "Hostel: Part II นรกรอชำแหละ 2 (2007)",
        "info": "บรรยายไทย",
        "image": "https://img.fw4free.com/postor/20250612180125vKzW1zixWWwvmPipevcetxsCmKA.jpg",
        "subtitle": "https://pastebin.com/raw/XjDpyhzb",
        "url": "https://m1free.inwstream.com:1936/movie4/Hostel_Part_II_2007/Hostel_Part_II_2007_st_1080.mp4/playlist.m3u8",
        "referer": "https://fw4free.com/"
    },
    {
        "name": "My Old Ass เชื่อตัวเองดีที่สุด! (ไหมนะ)",
        "info": "พากย์ไทย",
        "image": "https://img.fw4free.com/postor/202506120801217zwM82MEilz58jgLZJTHcF4aY8S.jpg",
        "subtitle": "https://pastebin.com/raw/XjDpyhzb",
        "url": "https://m1free.inwstream.com:1936/movie4/My_Old_Ass_2024/My_Old_Ass_2024_TH_1080p.mp4/playlist.m3u8",
        "referer": "https://fw4free.com/"
    },
    {
        "name": "My Old Ass เชื่อตัวเองดีที่สุด! (ไหมนะ)",
        "info": "บรรยายไทย",
        "image": "https://img.fw4free.com/postor/202506120801217zwM82MEilz58jgLZJTHcF4aY8S.jpg",
        "subtitle": "https://pastebin.com/raw/XjDpyhzb",
        "url": "https://m1free.inwstream.com:1936/movie4/My_Old_Ass_2024/My_Old_Ass_2024_EN_1080p.mp4/playlist.m3u8",
        "referer": "https://fw4free.com/"
    },
    {
        "name": "Our Friend สุขทุกข์ เพื่อนเราไม่ห่างกัน (2019)",
        "info": "พากย์ไทย",
        "image": "https://img.fw4free.com/postor/20250611184209vg9C5LttsKBqoLuqeQvOXaeBGiD.jpg",
        "subtitle": "https://pastebin.com/raw/XjDpyhzb",
        "url": "https://m1free.inwstream.com:1936/movie3/Our_Friend_2019/Our_Friend_2019_th_1080.mp4/playlist.m3u8",
        "referer": "https://fw4free.com/"
    },
    {
        "name": "Our Friend สุขทุกข์ เพื่อนเราไม่ห่างกัน (2019)",
        "info": "บรรยายไทย",
        "image": "https://img.fw4free.com/postor/20250611184209vg9C5LttsKBqoLuqeQvOXaeBGiD.jpg",
        "subtitle": "https://pastebin.com/raw/XjDpyhzb",
        "url": "https://m1free.inwstream.com:1936/movie3/Our_Friend_2019/Our_Friend_2019_st_1080.mp4/playlist.m3u8",
        "referer": "https://fw4free.com/"
    },
    {
        "name": "Cheers to Life (Viva a Vida)",
        "info": "พากย์ไทย",
        "image": "https://img.fw4free.com/postor/20250611171234505256869_122195551424277025_703780616846666898_n.jpg",
        "subtitle": "https://pastebin.com/raw/XjDpyhzb",
        "url": "https://m1free.inwstream.com:1936/movie4/Cheers_to_Life_2024/Cheers_to_Life_2024_TH_1080p.mp4/playlist.m3u8",
        "referer": "https://fw4free.com/"
    },
    {
        "name": "Cheers to Life (Viva a Vida)",
        "info": "บรรยายไทย",
        "image": "https://img.fw4free.com/postor/20250611171234505256869_122195551424277025_703780616846666898_n.jpg",
        "subtitle": "https://pastebin.com/raw/XjDpyhzb",
        "url": "https://m1free.inwstream.com:1936/movie4/Cheers_to_Life_2024/Cheers_to_Life_2024_ST_1080p.mp4/playlist.m3u8",
        "referer": "https://fw4free.com/"
    },
    {
        "name": "Our Times (Nuestros Tiempos)",
        "info": "บรรยายไทย",
        "image": "https://img.fw4free.com/postor/20250611170229t0AEaR2N7ZqMJuROWTYShOOkm3o.jpg",
        "subtitle": "https://pastebin.com/raw/XjDpyhzb",
        "url": "https://m1free.inwstream.com:1936/movie4/Our_Times_2025/Our_Times_2025_ST_1080p.mp4/playlist.m3u8",
        "referer": "https://fw4free.com/"
    },
    {
        "name": "Titan: The OceanGate Disaster วิบัติโอเชียนเกต (2025)",
        "info": "บรรยายไทย",
        "image": "https://img.fw4free.com/postor/20250611160508mSVJI9P5UmvOLZVTH8sAtlgxsgy.jpg",
        "subtitle": "https://pastebin.com/raw/XjDpyhzb",
        "url": "https://m1free.inwstream.com:1936/movie4/Titan_The_OceanGate_Disaster_2025/Titan_The_OceanGate_Disaster_2025_EN_1080p.mp4/playlist.m3u8",
        "referer": "https://fw4free.com/"
    },
    {
        "name": "Snow White สโนว์ไวท์ (2025)",
        "info": "พากย์ไทย",
        "image": "https://img.fw4free.com/postor/20250611155445oLxWocqheC8XbXbxqJ3x422j9PW.jpg",
        "subtitle": "https://pastebin.com/raw/XjDpyhzb",
        "url": "https://m1free.inwstream.com:1936/movie4/Snow_White_2025/Snow_White_2025_TH_1080p_1.mp4/playlist.m3u8",
        "referer": "https://fw4free.com/"
    },
    {
        "name": "Snow White สโนว์ไวท์ (2025)",
        "info": "บรรยายไทย",
        "image": "https://img.fw4free.com/postor/20250611155445oLxWocqheC8XbXbxqJ3x422j9PW.jpg",
        "subtitle": "https://pastebin.com/raw/XjDpyhzb",
        "url": "https://m1free.inwstream.com:1936/movie4/Snow_White_2025/Snow_White_2025_EN_1080p_1.mp4/playlist.m3u8",
        "referer": "https://fw4free.com/"
    },
    {
        "name": "The Four Feathers เกียรติศักดิ์นักรบคู่แผ่นดิน (2002)",
        "info": "บรรยายไทย",
        "image": "https://img.fw4free.com/postor/20250611103012bfmpeRr9LTXzBC2dpC89FE5uavK.jpg",
        "subtitle": "https://pastebin.com/raw/XjDpyhzb",
        "url": "https://m1free.inwstream.com:1936/movie4/The_Four_Feathers_2002/The_Four_Feathers_2002_EN_1080p.mp4/playlist.m3u8",
        "referer": "https://fw4free.com/"
    },
    {
        "name": "Trainwreck: The Astroworld Tragedy อภิมหาวายป่วง: โศกนาฏกรรมแอสโทรเวิลด์ (2025)",
        "info": "บรรยายไทย",
        "image": "https://img.fw4free.com/postor/20250611083732ouvMuuZEx1TAiq2F9rcFBwFdxp6.jpg",
        "subtitle": "https://pastebin.com/raw/XjDpyhzb",
        "url": "https://m1free.inwstream.com:1936/movie4/Trainwreck_The_Astroworld_Tragedy_2025/Trainwreck_The_Astroworld_Tragedy_2025_EN_1080p.mp4/playlist.m3u8",
        "referer": "https://fw4free.com/"
    },
    {
        "name": "All the Pretty Horses สุภาพบุรุษอาชา (2000)",
        "info": "บรรยายไทย",
        "image": "https://img.fw4free.com/postor/202506101022456E4E7wYXw1DE2321F2hVNryLSk7.jpg",
        "subtitle": "https://pastebin.com/raw/XjDpyhzb",
        "url": "https://m1free.inwstream.com:1936/movie4/All_the_Pretty_Horses_2000/All_the_Pretty_Horses_2000_EN_1080p.mp4/playlist.m3u8",
        "referer": "https://fw4free.com/"
    },
    {
        "name": "Broke ขุมเยือกแข็ง (2025)",
        "info": "บรรยายไทย",
        "image": "https://img.fw4free.com/postor/202506092103145RtialbsouT4IECGt8NpN7Zumsv.jpg",
        "subtitle": "https://pastebin.com/raw/XjDpyhzb",
        "url": "https://m1free.inwstream.com:1936/movie4/Broke_2025/Broke_2025_st_1080.mp4/playlist.m3u8",
        "referer": "https://fw4free.com/"
    },
    {
        "name": "The Alto Knights อัลโต ไนท์ส: ทรชนครองเมือง (2025)",
        "info": "พากย์ไทย",
        "image": "https://img.fw4free.com/postor/2025060919550595KmR0xNuZZ6DNESDwLKWGIBvMg.jpg",
        "subtitle": "https://pastebin.com/raw/XjDpyhzb",
        "url": "https://m1free.inwstream.com:1936/movie4/The_Alto_Knights_2025/The_Alto_Knights_2025_th_1080.mp4/playlist.m3u8",
        "referer": "https://fw4free.com/"
    },
    {
        "name": "The Alto Knights อัลโต ไนท์ส: ทรชนครองเมือง (2025)",
        "info": "บรรยายไทย",
        "image": "https://img.fw4free.com/postor/2025060919550595KmR0xNuZZ6DNESDwLKWGIBvMg.jpg",
        "subtitle": "https://pastebin.com/raw/XjDpyhzb",
        "url": "https://m1free.inwstream.com:1936/movie4/The_Alto_Knights_2025/The_Alto_Knights_2025_st_1080.mp4/playlist.m3u8",
        "referer": "https://fw4free.com/"
    },
    {
        "name": "Humane นี่นะเหรอ...มนุษยธรรม (2024)",
        "info": "พากย์ไทย",
        "image": "https://img.fw4free.com/postor/20250609194800ecOvKaoM1hwQbp0uTnULGrSV32e.jpg",
        "subtitle": "https://pastebin.com/raw/XjDpyhzb",
        "url": "https://m1free.inwstream.com:1936/movie4/Humane_2024/Humane_2024_th_1080.mp4/playlist.m3u8",
        "referer": "https://fw4free.com/"
    },
    {
        "name": "Humane นี่นะเหรอ...มนุษยธรรม (2024)",
        "info": "บรรยายไทย",
        "image": "https://img.fw4free.com/postor/20250609194800ecOvKaoM1hwQbp0uTnULGrSV32e.jpg",
        "subtitle": "https://pastebin.com/raw/XjDpyhzb",
        "url": "https://m1free.inwstream.com:1936/movie4/Humane_2024/Humane_2024_st_1080.mp4/playlist.m3u8",
        "referer": "https://fw4free.com/"
    },
    {
        "name": "Ocean with David Attenborough (2025)",
        "info": "บรรยายไทย",
        "image": "https://img.fw4free.com/postor/20250609103317zL4nDb0brgF99zLvpW43gL1EVnT.jpg",
        "subtitle": "https://pastebin.com/raw/XjDpyhzb",
        "url": "https://m1free.inwstream.com:1936/movie4/Ocean_with_David_Attenborough_2025/Ocean_with_David_Attenborough_2025_EN_1080p.mp4/playlist.m3u8",
        "referer": "https://fw4free.com/"
    },
    {
        "name": "Straw ฟางเส้นสุดท้าย (2025)",
        "info": "พากย์ไทย",
        "image": "https://img.fw4free.com/postor/20250606153800t3cmnXYtxJb9vVL1ThvT2CWSe1n.jpg",
        "subtitle": "https://pastebin.com/raw/XjDpyhzb",
        "url": "https://m1free.inwstream.com:1936/movie4/Straw_2025/Straw_2025_TH_1080p.mp4/playlist.m3u8",
        "referer": "https://fw4free.com/"
    },
    {
        "name": "Straw ฟางเส้นสุดท้าย (2025)",
        "info": "บรรยายไทย",
        "image": "https://img.fw4free.com/postor/20250606153800t3cmnXYtxJb9vVL1ThvT2CWSe1n.jpg",
        "subtitle": "https://pastebin.com/raw/XjDpyhzb",
        "url": "https://m1free.inwstream.com:1936/movie4/Straw_2025/Straw_2025_EN_1080p.mp4/playlist.m3u8",
        "referer": "https://fw4free.com/"
    },
    {
        "name": "K.O. น็อกเอาท์ (2025)",
        "info": "พากย์ไทย",
        "image": "https://img.fw4free.com/postor/20250606152701kXZIt6sSsWMgkyan0boj72WZlpt.jpg",
        "subtitle": "https://pastebin.com/raw/XjDpyhzb",
        "url": "https://m1free.inwstream.com:1936/movie4/K_O_2025/K_O_2025_TH_1080p.mp4/playlist.m3u8",
        "referer": "https://fw4free.com/"
    },
    {
        "name": "K.O. น็อกเอาท์ (2025)",
        "info": "บรรยายไทย",
        "image": "https://img.fw4free.com/postor/20250606152701kXZIt6sSsWMgkyan0boj72WZlpt.jpg",
        "subtitle": "https://pastebin.com/raw/XjDpyhzb",
        "url": "https://m1free.inwstream.com:1936/movie4/K_O_2025/K_O_2025_ST_1080p.mp4/playlist.m3u8",
        "referer": "https://fw4free.com/"
    },
    {
        "name": "Sideways ไซด์เวยส์ ดื่มชีวิต ข้างทาง (2004)",
        "info": "พากย์ไทย",
        "image": "https://img.fw4free.com/postor/20250606091445ERE8JdnKWbLGkhCpGUT68I7tNp.jpg",
        "subtitle": "https://pastebin.com/raw/XjDpyhzb",
        "url": "https://m1free.inwstream.com:1936/movie4/Sideways_2004/Sideways_2004_TH_1080p.mp4/playlist.m3u8",
        "referer": "https://fw4free.com/"
    },
    {
        "name": "Sideways ไซด์เวยส์ ดื่มชีวิต ข้างทาง (2004)",
        "info": "บรรยายไทย",
        "image": "https://img.fw4free.com/postor/20250606091445ERE8JdnKWbLGkhCpGUT68I7tNp.jpg",
        "subtitle": "https://pastebin.com/raw/XjDpyhzb",
        "url": "https://m1free.inwstream.com:1936/movie4/Sideways_2004/Sideways_2004_EN_1080p.mp4/playlist.m3u8",
        "referer": "https://fw4free.com/"
    },
    {
        "name": "The Accountant 2 อัจฉริยะคนบัญชีเพชฌฆาต 2 (2025)",
        "info": "พากย์ไทย",
        "image": "https://img.fw4free.com/postor/20250605150029kMDUS7VmFhb2coRfVBoGLR8ADBt.jpg",
        "subtitle": "https://pastebin.com/raw/XjDpyhzb",
        "url": "https://m1free.inwstream.com:1936/movie4/The_Accountant_2_2025/The_Accountant_2_2025_TH_1080p.mp4/playlist.m3u8",
        "referer": "https://fw4free.com/"
    },
    {
        "name": "The Accountant 2 อัจฉริยะคนบัญชีเพชฌฆาต 2 (2025)",
        "info": "บรรยายไทย",
        "image": "https://img.fw4free.com/postor/20250605150029kMDUS7VmFhb2coRfVBoGLR8ADBt.jpg",
        "subtitle": "https://pastebin.com/raw/XjDpyhzb",
        "url": "https://m1free.inwstream.com:1936/movie4/The_Accountant_2_2025/The_Accountant_2_2025_EN_1080p.mp4/playlist.m3u8",
        "referer": "https://fw4free.com/"
    },
    {
        "name": "Bordello of Blood คืนนรกแตก 2 (1996)",
        "info": "พากย์ไทย",
        "image": "https://img.fw4free.com/postor/20241118033312aKkUQ0Zd9TFlqfcMMHFKQBB15wZ.jpg",
        "subtitle": "https://pastebin.com/raw/XjDpyhzb",
        "url": "https://m1free.inwstream.com:1936/movie4/Bordello_of_Blood_1996/Bordello_of_Blood_1996_th_1080.mp4/playlist.m3u8",
        "referer": "https://fw4free.com/"
    },
    {
        "name": "Bordello of Blood คืนนรกแตก 2 (1996)",
        "info": "บรรยายไทย",
        "image": "https://img.fw4free.com/postor/20241118033312aKkUQ0Zd9TFlqfcMMHFKQBB15wZ.jpg",
        "subtitle": "https://pastebin.com/raw/XjDpyhzb",
        "url": "https://m1free.inwstream.com:1936/movie4/Bordello_of_Blood_1996/Bordello_of_Blood_1996_EN_1080p_T.mp4/playlist.m3u8",
        "referer": "https://fw4free.com/"
    },
    {
        "name": "Baghead ผีสิงผี (2023)",
        "info": "บรรยายไทย",
        "image": "https://img.fw4free.com/postor/20250605083237lbOyeiiRYAE6Nm2e7xiNAAaRwZB.jpg",
        "subtitle": "https://pastebin.com/raw/XjDpyhzb",
        "url": "https://m1free.inwstream.com:1936/movie4/Baghead_2023/Baghead_2023_EN_1080p_T_1.mp4/playlist.m3u8",
        "referer": "https://fw4free.com/"
    },
    {
        "name": "Thin Ice (The Convincer)",
        "info": "พากย์ไทย",
        "image": "https://img.fw4free.com/postor/2025060409505515KTuJlR8GclVrgX0g58oACqiqv.jpg",
        "subtitle": "https://pastebin.com/raw/XjDpyhzb",
        "url": "https://m1free.inwstream.com:1936/movie4/Thin_Ice_2011/Thin_Ice_2011_TH_1080p.mp4/playlist.m3u8",
        "referer": "https://fw4free.com/"
    },
    {
        "name": "Thin Ice (The Convincer)",
        "info": "บรรยายไทย",
        "image": "https://img.fw4free.com/postor/2025060409505515KTuJlR8GclVrgX0g58oACqiqv.jpg",
        "subtitle": "https://pastebin.com/raw/XjDpyhzb",
        "url": "https://m1free.inwstream.com:1936/movie4/Thin_Ice_2011/Thin_Ice_2011_EN_1080p.mp4/playlist.m3u8",
        "referer": "https://fw4free.com/"
    },
    {
        "name": "An American Crime ซิลเวียร์เหยื่ออยุติธรรม (2007)",
        "info": "บรรยายไทย",
        "image": "https://img.fw4free.com/postor/20250603103943bLsE0sMI1bycBxZX7QNYghy5iyi.jpg",
        "subtitle": "https://pastebin.com/raw/XjDpyhzb",
        "url": "https://m1free.inwstream.com:1936/movie4/An_American_Crime_2007/An_American_Crime_2007_EN_1080p_T.mp4/playlist.m3u8",
        "referer": "https://fw4free.com/"
    },
    {
        "name": "Trouble Every Day (Sangre caníbal)",
        "info": "บรรยายไทย",
        "image": "https://img.fw4free.com/postor/20250603102851z7oOCixexPW8Kb0MauCd1EsaqsJ.jpg",
        "subtitle": "https://pastebin.com/raw/XjDpyhzb",
        "url": "https://m1free.inwstream.com:1936/movie4/Trouble_Every_Day_2001/Trouble_Every_Day_2001_EN_1080p_T.mp4/playlist.m3u8",
        "referer": "https://fw4free.com/"
    },
    {
        "name": "Sinners ซินเนอร์ส (2025)",
        "info": "พากย์ไทย",
        "image": "https://img.fw4free.com/postor/20250418160525yqsCU5XOP2mkbFamzAqbqntmfav.jpg",
        "subtitle": "https://pastebin.com/raw/XjDpyhzb",
        "url": "https://m1free.inwstream.com:1936/movie4/Sinners_2025/Sinners_2025_th_1080_A.mp4/playlist.m3u8",
        "referer": "https://fw4free.com/"
    },
    {
        "name": "Sinners ซินเนอร์ส (2025)",
        "info": "บรรยายไทย",
        "image": "https://img.fw4free.com/postor/20250418160525yqsCU5XOP2mkbFamzAqbqntmfav.jpg",
        "subtitle": "https://pastebin.com/raw/XjDpyhzb",
        "url": "https://m1free.inwstream.com:1936/movie4/Sinners_2025/Sinners_2025_st_1080_A.mp4/playlist.m3u8",
        "referer": "https://fw4free.com/"
    },
    {
        "name": "The Unbreakable Boy เด็กชายหัวใจไม่แพ้ (2025)",
        "info": "บรรยายไทย",
        "image": "https://img.fw4free.com/postor/20250603015107ob1cuQzzggELGtWx5TchixKsBVn.jpg",
        "subtitle": "https://pastebin.com/raw/XjDpyhzb",
        "url": "https://m1free.inwstream.com:1936/movie4/The_Unbreakable_Boy_2025/The_Unbreakable_Boy_2025_st_1080.mp4/playlist.m3u8",
        "referer": "https://fw4free.com/"
    },
    {
        "name": "Mountainhead เมาน์เทนเฮด (2025)",
        "info": "บรรยายไทย",
        "image": "https://img.fw4free.com/postor/20250602110257jZKK5mFKWbquxhAGMkRJtNYwk0I.jpg",
        "subtitle": "https://pastebin.com/raw/XjDpyhzb",
        "url": "https://m1free.inwstream.com:1936/movie4/Mountainhead_2025/Mountainhead_2025_EN_1080p.mp4/playlist.m3u8",
        "referer": "https://fw4free.com/"
    },
    {
        "name": "I Saw the TV Glow จิตจ้องจอ (2024)",
        "info": "พากย์ไทย",
        "image": "https://img.fw4free.com/postor/20240806203349a6ybCvFEr2DNt0H9z5cO1L27WYG.jpg",
        "subtitle": "https://pastebin.com/raw/XjDpyhzb",
        "url": "https://m1free.inwstream.com:1936/movie4/I_Saw_the_TV_Glow_2024/I_Saw_the_TV_Glow_2024_TH_1080p_1.mp4/playlist.m3u8",
        "referer": "https://fw4free.com/"
    },
    {
        "name": "I Saw the TV Glow จิตจ้องจอ (2024)",
        "info": "บรรยายไทย",
        "image": "https://img.fw4free.com/postor/20240806203349a6ybCvFEr2DNt0H9z5cO1L27WYG.jpg",
        "subtitle": "https://pastebin.com/raw/XjDpyhzb",
        "url": "https://m1free.inwstream.com:1936/movie4/I_Saw_the_TV_Glow_2024/I_Saw_the_TV_Glow_2024_st_1080.mp4/playlist.m3u8",
        "referer": "https://fw4free.com/"
    },
    {
        "name": "We Need a Little Christmas คริสต์มาสนี้ไม่ไร้รัก (2022)",
        "info": "พากย์ไทย",
        "image": "https://img.fw4free.com/postor/20250602030645n2TIUpxs4I9cfNOqVx8LVvg9qye.jpg",
        "subtitle": "https://pastebin.com/raw/XjDpyhzb",
        "url": "https://m1free.inwstream.com:1936/movie3/We_Need_a_Little_Christmas_2022/We_Need_a_Little_Christmas_2022_th_1080p.mp4/playlist.m3u8",
        "referer": "https://fw4free.com/"
    },
    {
        "name": "We Need a Little Christmas คริสต์มาสนี้ไม่ไร้รัก (2022)",
        "info": "บรรยายไทย",
        "image": "https://img.fw4free.com/postor/20250602030645n2TIUpxs4I9cfNOqVx8LVvg9qye.jpg",
        "subtitle": "https://pastebin.com/raw/XjDpyhzb",
        "url": "https://m1free.inwstream.com:1936/movie3/We_Need_a_Little_Christmas_2022/We_Need_a_Little_Christmas_2022_st_1080p.mp4/playlist.m3u8",
        "referer": "https://fw4free.com/"
    },
    {
        "name": "Unsung Hero รัก ฝัน ศรัทธา (2024)",
        "info": "พากย์ไทย",
        "image": "https://img.fw4free.com/postor/20240719210309wKYrat0neU4sHl8aO4BCzxCKFQy.jpg",
        "subtitle": "https://pastebin.com/raw/XjDpyhzb",
        "url": "https://m1free.inwstream.com:1936/movie4/Unsung_Hero_2024/Unsung_Hero_2024_th_1080.mp4/playlist.m3u8",
        "referer": "https://fw4free.com/"
    },
    {
        "name": "Unsung Hero รัก ฝัน ศรัทธา (2024)",
        "info": "บรรยายไทย",
        "image": "https://img.fw4free.com/postor/20240719210309wKYrat0neU4sHl8aO4BCzxCKFQy.jpg",
        "subtitle": "https://pastebin.com/raw/XjDpyhzb",
        "url": "https://m1free.inwstream.com:1936/movie4/Unsung_Hero_2024/Unsung_Hero_2024_st_1080.mp4/playlist.m3u8",
        "referer": "https://fw4free.com/"
    },
    {
        "name": "The Persian Version เดอะเปอร์เซียนเวอร์ชั่น (2023)",
        "info": "พากย์ไทย",
        "image": "https://img.fw4free.com/postor/202506020259311nzBlZtebWJXY8ap0ibkgb3eMUr.jpg",
        "subtitle": "https://pastebin.com/raw/XjDpyhzb",
        "url": "https://m1free.inwstream.com:1936/movie3/The_Persian_Version_2023/The_Persian_Version_2023_th_1080.mp4/playlist.m3u8",
        "referer": "https://fw4free.com/"
    },
    {
        "name": "The Persian Version เดอะเปอร์เซียนเวอร์ชั่น (2023)",
        "info": "บรรยายไทย",
        "image": "https://img.fw4free.com/postor/202506020259311nzBlZtebWJXY8ap0ibkgb3eMUr.jpg",
        "subtitle": "https://pastebin.com/raw/XjDpyhzb",
        "url": "https://m1free.inwstream.com:1936/movie3/The_Persian_Version_2023/The_Persian_Version_2023_st_1080.mp4/playlist.m3u8",
        "referer": "https://fw4free.com/"
    },
    {
        "name": "Someone Like You ดุจดังเธอในดวงใจ (2024)",
        "info": "พากย์ไทย",
        "image": "https://img.fw4free.com/postor/20240827004309zsvD0BjEQIIoh2PpE5X7VXmSrQO.jpg",
        "subtitle": "https://pastebin.com/raw/XjDpyhzb",
        "url": "https://m1free.inwstream.com:1936/movie4/Someone_Like_You_2024/Someone_Like_You_2024_th_1080.mp4/playlist.m3u8",
        "referer": "https://fw4free.com/"
    },
    {
        "name": "Someone Like You ดุจดังเธอในดวงใจ (2024)",
        "info": "บรรยายไทย",
        "image": "https://img.fw4free.com/postor/20240827004309zsvD0BjEQIIoh2PpE5X7VXmSrQO.jpg",
        "subtitle": "https://pastebin.com/raw/XjDpyhzb",
        "url": "https://m1free.inwstream.com:1936/movie4/Someone_Like_You_2024/Someone_Like_You_2024_st_1080.mp4/playlist.m3u8",
        "referer": "https://fw4free.com/"
    },
    {
        "name": "Romance In Style โรแมนซ์ อิน สไตล์ (2022)",
        "info": "พากย์ไทย",
        "image": "https://img.fw4free.com/postor/20250602025454gYcVRws4Hu5B36ji7BheKDnSbfP.jpg",
        "subtitle": "https://pastebin.com/raw/XjDpyhzb",
        "url": "https://m1free.inwstream.com:1936/movie3/Romance_In_Style_2022/Romance_In_Style_2022_th_1080p.mp4/playlist.m3u8",
        "referer": "https://fw4free.com/"
    },
    {
        "name": "Romance In Style โรแมนซ์ อิน สไตล์ (2022)",
        "info": "บรรยายไทย",
        "image": "https://img.fw4free.com/postor/20250602025454gYcVRws4Hu5B36ji7BheKDnSbfP.jpg",
        "subtitle": "https://pastebin.com/raw/XjDpyhzb",
        "url": "https://m1free.inwstream.com:1936/movie3/Romance_In_Style_2022/Romance_In_Style_2022_st_1080p.mp4/playlist.m3u8",
        "referer": "https://fw4free.com/"
    },
    {
        "name": "The Bikeriders เดอะ ไบค์ไรเดอร์ส (2023)",
        "info": "พากย์ไทย",
        "image": "https://img.fw4free.com/postor/20240830175317qTb6sSRt8Pw96JTan8ezU2xO0FU.jpg",
        "subtitle": "https://pastebin.com/raw/XjDpyhzb",
        "url": "https://m1free.inwstream.com:1936/movie4/The_Bikeriders_2023/The_Bikeriders_2023_TH_1080p.mp4/playlist.m3u8",
        "referer": "https://fw4free.com/"
    },
    {
        "name": "The Bikeriders เดอะ ไบค์ไรเดอร์ส (2023)",
        "info": "บรรยายไทย",
        "image": "https://img.fw4free.com/postor/20240830175317qTb6sSRt8Pw96JTan8ezU2xO0FU.jpg",
        "subtitle": "https://pastebin.com/raw/XjDpyhzb",
        "url": "https://m1free.inwstream.com:1936/movie4/The_Bikeriders_2023/The_Bikeriders_2023_st_1080.mp4/playlist.m3u8",
        "referer": "https://fw4free.com/"
    },
    {
        "name": "Spies Like Us สปายเป๋อสปายเปิ่น (1985)",
        "info": "พากย์ไทย",
        "image": "https://img.fw4free.com/postor/20250601095811s0Sx8nd9Irq0aCPbsN78s0DYVlG.jpg",
        "subtitle": "https://pastebin.com/raw/XjDpyhzb",
        "url": "https://m1free.inwstream.com:1936/movie4/Spies_Like_Us_1985/Spies_Like_Us_1985_TH_1080p.mp4/playlist.m3u8",
        "referer": "https://fw4free.com/"
    },
    {
        "name": "Spies Like Us สปายเป๋อสปายเปิ่น (1985)",
        "info": "บรรยายไทย",
        "image": "https://img.fw4free.com/postor/20250601095811s0Sx8nd9Irq0aCPbsN78s0DYVlG.jpg",
        "subtitle": "https://pastebin.com/raw/XjDpyhzb",
        "url": "https://m1free.inwstream.com:1936/movie4/Spies_Like_Us_1985/Spies_Like_Us_1985_EN_1080p_T.mp4/playlist.m3u8",
        "referer": "https://fw4free.com/"
    },
    {
        "name": "Graduation Trip: Mallorca (Viaje de fin de curso: Mallorca)",
        "info": "พากย์ไทย",
        "image": "https://img.fw4free.com/postor/20250531092308ejYX4ygRoupGRjFgmmtnK0sMxhN.jpg",
        "subtitle": "https://pastebin.com/raw/XjDpyhzb",
        "url": "https://m1free.inwstream.com:1936/movie4/Graduation_Trip_Mallorca_2025/Graduation_Trip_Mallorca_2025_TH_1080p.mp4/playlist.m3u8",
        "referer": "https://fw4free.com/"
    },
    {
        "name": "Graduation Trip: Mallorca (Viaje de fin de curso: Mallorca)",
        "info": "บรรยายไทย",
        "image": "https://img.fw4free.com/postor/20250531092308ejYX4ygRoupGRjFgmmtnK0sMxhN.jpg",
        "subtitle": "https://pastebin.com/raw/XjDpyhzb",
        "url": "https://m1free.inwstream.com:1936/movie4/Graduation_Trip_Mallorca_2025/Graduation_Trip_Mallorca_2025_ST_1080p.mp4/playlist.m3u8",
        "referer": "https://fw4free.com/"
    },
    {
        "name": "The Heart Knows (Corazón delator)",
        "info": "พากย์ไทย",
        "image": "https://img.fw4free.com/postor/20250530160638syHnruCgN1Gq6PJ5PcwxZg9BQWY.jpg",
        "subtitle": "https://pastebin.com/raw/XjDpyhzb",
        "url": "https://m1free.inwstream.com:1936/movie4/The_Heart_Knows_2025/The_Heart_Knows_2025_TH_1080p.mp4/playlist.m3u8",
        "referer": "https://fw4free.com/"
    },
    {
        "name": "The Heart Knows (Corazón delator)",
        "info": "บรรยายไทย",
        "image": "https://img.fw4free.com/postor/20250530160638syHnruCgN1Gq6PJ5PcwxZg9BQWY.jpg",
        "subtitle": "https://pastebin.com/raw/XjDpyhzb",
        "url": "https://m1free.inwstream.com:1936/movie4/The_Heart_Knows_2025/The_Heart_Knows_2025_ST_1080p.mp4/playlist.m3u8",
        "referer": "https://fw4free.com/"
    },
    {
        "name": "A Widow's Game (La viuda negra)",
        "info": "พากย์ไทย",
        "image": "https://img.fw4free.com/postor/20250530160303yZOdrJDl2GwREoigC0y40kMosxj.jpg",
        "subtitle": "https://pastebin.com/raw/XjDpyhzb",
        "url": "https://m1free.inwstream.com:1936/movie4/A_Widow_s_Game_2025/A_Widow_s_Game_2025_TH_1080p.mp4/playlist.m3u8",
        "referer": "https://fw4free.com/"
    },
    {
        "name": "A Widow's Game (La viuda negra)",
        "info": "บรรยายไทย",
        "image": "https://img.fw4free.com/postor/20250530160303yZOdrJDl2GwREoigC0y40kMosxj.jpg",
        "subtitle": "https://pastebin.com/raw/XjDpyhzb",
        "url": "https://m1free.inwstream.com:1936/movie4/A_Widow_s_Game_2025/A_Widow_s_Game_2025_ST_1080p.mp4/playlist.m3u8",
        "referer": "https://fw4free.com/"
    },
    {
        "name": "Death of a Unicorn (2025)",
        "info": "บรรยายไทย",
        "image": "https://img.fw4free.com/postor/20250530063513lXR32JepFwD1UHkplWqtBP1K79z.jpg",
        "subtitle": "https://pastebin.com/raw/XjDpyhzb",
        "url": "https://m1free.inwstream.com:1936/movie4/Death_of_a_Unicorn_2025/Death_of_a_Unicorn_2025_st_1080_SAI.mp4/playlist.m3u8",
        "referer": "https://fw4free.com/"
    },
    {
        "name": "Revenge แค้นนี้ต้องทวงคืน (1990)",
        "info": "บรรยายไทย",
        "image": "https://img.fw4free.com/postor/20250530060553nuB1VoB46BLvM0ae3tbGSWhzV0E.jpg",
        "subtitle": "https://pastebin.com/raw/XjDpyhzb",
        "url": "https://m1free.inwstream.com:1936/movie4/Revenge_1990/Revenge_1990_st_1080upscal_2.mp4/playlist.m3u8",
        "referer": "https://fw4free.com/"
    },
	{
   "name": "LEGO Jurassic Park: The Unofficial Retelling (2023)",
   "info": "บรรยายไทย",
   "image": "https://img.fw4free.com/postor/20240225185253xSq8TrEqz8NRyWJSviteKE1t249.jpg",
   "subtitle": "https://pastebin.com/raw/XjDpyhzb",
   "url": "https://m1free.inwstream.com:1936/movie3/LEGO_Jurassic_Park_The_Unofficial_Retelling_2023/LEGO_Jurassic_Park_The_Unofficial_Retelling_2023_st_1080.mp4/playlist.m3u8",
   "referer": "https://fw4free.com/"
  },

  {
   "name": "Jurassic World Camp Cretaceous: Hidden Adventure จูราสสิค เวิลด์ ค่ายครีเทเชียส: การผจญภัยซ่อนเร้น (2022)",
   "info": "พากย์ไทย",
   "image": "https://img.fw4free.com/postor/20221116220955d355r4gpQj1HnwGfnhUbm0c7x4o.jpg",
   "subtitle": "https://pastebin.com/raw/XjDpyhzb",
   "url": "https://m1free.inwstream.com:1936/movie3/Jurassic_World_Camp_Cretaceous_Hidden_Adventure_2022/Jurassic_World_Camp_Cretaceous_Hidden_Adventure_2022_th_1080p.mp4/playlist.m3u8",
   "referer": "https://fw4free.com/"
  },
  {
   "name": "Jurassic World Camp Cretaceous: Hidden Adventure จูราสสิค เวิลด์ ค่ายครีเทเชียส: การผจญภัยซ่อนเร้น (2022)",
   "info": "บรรยายไทย",
   "image": "https://img.fw4free.com/postor/20221116220955d355r4gpQj1HnwGfnhUbm0c7x4o.jpg",
   "subtitle": "https://pastebin.com/raw/XjDpyhzb",
   "url": "https://m1free.inwstream.com:1936/movie3/Jurassic_World_Camp_Cretaceous_Hidden_Adventure_2022/Jurassic_World_Camp_Cretaceous_Hidden_Adventure_2022_st_1080p.mp4/playlist.m3u8",
   "referer": "https://fw4free.com/"
  },
  {
   "name": "Jurassic World Dominion จูราสสิค เวิลด์ ทวงคืนอาณาจักร (2022)",
   "info": "พากย์ไทย",
   "image": "https://img.fw4free.com/postor/20220812160453kAVRgw7GgK1CfYEJq8ME6EvRIgU.jpg",
   "subtitle": "https://pastebin.com/raw/XjDpyhzb",
   "url": "https://m1free.inwstream.com:1936/movie3/Jurassic_World_Dominion_2022/Jurassic_World_Dominion_2022_th_1080p_F.mp4/playlist.m3u8",
   "referer": "https://fw4free.com/"
  },
  {
   "name": "Jurassic World Dominion จูราสสิค เวิลด์ ทวงคืนอาณาจักร (2022)",
   "info": "บรรยายไทย",
   "image": "https://img.fw4free.com/postor/20220812160453kAVRgw7GgK1CfYEJq8ME6EvRIgU.jpg",
   "subtitle": "https://pastebin.com/raw/XjDpyhzb",
   "url": "https://m1free.inwstream.com:1936/movie3/Jurassic_World_Dominion_2022/Jurassic_World_Dominion_2022_en_1080p.mp4/playlist.m3u8",
   "referer": "https://fw4free.com/"
  },


  {
   "name": "Jurassic World: Fallen Kingdom จูราสสิค เวิลด์: อาณาจักรล่มสลาย (2018)",
   "info": "พากย์ไทย",
   "image": "https://img.fw4free.com/postor/20180916103407jurassic-world-fallen-kingdom-5b25a6cb139e8.jpg",
   "subtitle": "https://pastebin.com/raw/XjDpyhzb",
   "url": "https://m1free.inwstream.com:1936/movie3/Jurassic_World_Fallen_Kingdom_2018_3D/Jurassic_World_Fallen_Kingdom_2018_TH_1080p_3D.mp4/playlist.m3u8",
   "referer": "https://fw4free.com/"
  },
  {
   "name": "Jurassic World: Fallen Kingdom จูราสสิค เวิลด์: อาณาจักรล่มสลาย (2018)",
   "info": "Soundtrack : Sub Thai",
   "image": "https://img.fw4free.com/postor/20180916103407jurassic-world-fallen-kingdom-5b25a6cb139e8.jpg",
   "subtitle": "https://pastebin.com/raw/XjDpyhzb",
   "url": "https://m1free.inwstream.com:1936/movie3/Jurassic_World_Fallen_Kingdom_2018_3D/Jurassic_World_Fallen_Kingdom_2018_EN_1080p_3D.mp4/playlist.m3u8",
   "referer": "https://fw4free.com/"
  },
  {
   "name": "Jurassic World: Fallen Kingdom จูราสสิค เวิลด์ อาณาจักรล่มสลาย (2018)",
   "info": "พากย์ไทย",
   "image": "https://img.fw4free.com/postor/20180928113039jurassic-world-fallen-kingdom-5b25a6cb139e8.jpg",
   "subtitle": "https://pastebin.com/raw/XjDpyhzb",
   "url": "https://m1free.inwstream.com:1936/movie3/Jurassic-World-Fallen-Kingdom-2018/Jurassic-World-Fallen-Kingdom-2018-TH-1080p.m4v/playlist.m3u8",
   "referer": "https://fw4free.com/"
  },
  {
   "name": "Jurassic World: Fallen Kingdom จูราสสิค เวิลด์ อาณาจักรล่มสลาย (2018)",
   "info": "Soundtrack : Sub Thai",
   "image": "https://img.fw4free.com/postor/20180928113039jurassic-world-fallen-kingdom-5b25a6cb139e8.jpg",
   "subtitle": "https://pastebin.com/raw/XjDpyhzb",
   "url": "https://m1free.inwstream.com:1936/movie3/Jurassic-World-Fallen-Kingdom-2018/Jurassic-World-Fallen-Kingdom-2018-EN-1080p.m4v/playlist.m3u8",
   "referer": "https://fw4free.com/"
  },
  {
   "name": "Jurassic World จูราสสิค เวิลด์ (2015)",
   "info": "พากย์ไทย",
   "image": "https://img.fw4free.com/postor/20200415123905Jurassic World จูราสสิค เวิลด์ (2015).jpg",
   "subtitle": "https://pastebin.com/raw/XjDpyhzb",
   "url": "https://m1free.inwstream.com:1936/movie2/Jurassic World (2015)/Jurassic World (2015) th 1080p fw.mp4/playlist.m3u8",
   "referer": "https://fw4free.com/"
  },
  {
   "name": "Jurassic World จูราสสิค เวิลด์ (2015)",
   "info": "SoundTrack+SubThai",
   "image": "https://img.fw4free.com/postor/20200415123905Jurassic World จูราสสิค เวิลด์ (2015).jpg",
   "subtitle": "https://pastebin.com/raw/XjDpyhzb",
   "url": "https://m1free.inwstream.com:1936/movie2/Jurassic World (2015)/Jurassic World (2015) en 1080p fw.mp4/playlist.m3u8",
   "referer": "https://fw4free.com/"
  },
  
  {
   "name": "Jurassic Park ไดโนเสาร์พันธุ์ดุ ",
   "info": "พากย์ไทย (ภาค1)",
   "image": "https://img.fw4free.com/postor/201401272308081.jpg",
   "subtitle": "https://pastebin.com/raw/XjDpyhzb",
   "url": "https://m1free.inwstream.com:1936/movie2/Jurassic Park 1-3/Jurassic Park 1 (1993) th 1080p fw.mp4/playlist.m3u8",
   "referer": "https://fw4free.com/"
  },
  {
   "name": "Jurassic Park ไดโนเสาร์พันธุ์ดุ ",
   "info": "SoundTrack+SubThai (ภาค1)",
   "image": "https://img.fw4free.com/postor/201401272308081.jpg",
   "subtitle": "https://pastebin.com/raw/XjDpyhzb",
   "url": "https://m1free.inwstream.com:1936/movie2/Jurassic Park 1-3/Jurassic Park 1 (1993) en 1080p fw.mp4/playlist.m3u8",
   "referer": "https://fw4free.com/"
  },
  {
   "name": "Jurassic Park ไดโนเสาร์พันธุ์ดุ 2",
   "info": "พากย์ไทย (ภาค2)",
   "image": "https://img.fw4free.com/postor/201401272308081.jpg",
   "subtitle": "https://pastebin.com/raw/XjDpyhzb",
   "url": "https://m1free.inwstream.com:1936/movie2/Jurassic Park 1-3/The Lost World Jurassic Park 2 (1997) th 1080p fw.mp4/playlist.m3u8",
   "referer": "https://fw4free.com/"
  },
  {
   "name": "Jurassic Park ไดโนเสาร์พันธุ์ดุ 2",
   "info": "SoundTrack+SubThai (ภาค2)",
   "image": "https://img.fw4free.com/postor/201401272308081.jpg",
   "subtitle": "https://pastebin.com/raw/XjDpyhzb",
   "url": "https://m1free.inwstream.com:1936/movie2/Jurassic Park 1-3/The Lost World Jurassic Park 2 (1997) en 1080p fw.mp4/playlist.m3u8",
   "referer": "https://fw4free.com/"
  },
  {
   "name": "Jurassic Park ไดโนเสาร์พันธุ์ดุ 3",
   "info": "พากย์ไทย (ภาค3)",
   "image": "https://img.fw4free.com/postor/201401272308081.jpg",
   "subtitle": "https://pastebin.com/raw/XjDpyhzb",
   "url": "https://m1free.inwstream.com:1936/movie2/Jurassic Park 1-3/Jurassic Park 3 (2001) th 1080p fw.mp4/playlist.m3u8",
   "referer": "https://fw4free.com/"
  },
  {
   "name": "Jurassic Park ไดโนเสาร์พันธุ์ดุ 3)",
   "info": "SoundTrack+SubThai (ภาค3)",
   "image": "https://img.fw4free.com/postor/201401272308081.jpg",
   "subtitle": "https://pastebin.com/raw/XjDpyhzb",
   "url": "https://m1free.inwstream.com:1936/movie2/Jurassic Park 1-3/Jurassic Park 3 (2001) en 1080p fw.mp4/playlist.m3u8",
   "referer": "https://fw4free.com/"
  },
  
    {
   "name": "Jurassic park 1 จูราสสิค ปาร์ค: กำเนิดใหม่ไดโนเสาร์ (1993)",
   "info": "พากย์ไทย",
   "image": "https://img.fw4free.com/postor/20200325125219Jurassic park 1 จูราสสิค ปาร์ค กำเนิดใหม่ไดโนเสาร์ (1993).jpg",
   "subtitle": "https://pastebin.com/raw/XjDpyhzb",
   "url": "https://m1free.inwstream.com:1936/movie2/Jurassic Park 1-3/Jurassic Park 1 (1993) th 1080p fw.mp4/playlist.m3u8",
   "referer": "https://fw4free.com/"
  },
  {
   "name": "Jurassic park 1 จูราสสิค ปาร์ค: กำเนิดใหม่ไดโนเสาร์ (1993)",
   "info": "SoundTrack : SubThai",
   "image": "https://img.fw4free.com/postor/20200325125219Jurassic park 1 จูราสสิค ปาร์ค กำเนิดใหม่ไดโนเสาร์ (1993).jpg",
   "subtitle": "https://pastebin.com/raw/XjDpyhzb",
   "url": "https://m1free.inwstream.com:1936/movie2/Jurassic Park 1-3/Jurassic Park 1 (1993) en 1080p fw.mp4/playlist.m3u8",
   "referer": "https://fw4free.com/"
  },
  {
   "name": "Jurassic park 2 The lost world ใครว่ามันสูญพันธุ์ จูราสสิคพาร์ค (1997)",
   "info": "พากย์ไทย",
   "image": "https://img.fw4free.com/postor/20200325124148Jurassic park 2 The lost world ใครว่ามันสูญพันธุ์ จูราสสิคพาร์ค(1997).jpg",
   "subtitle": "https://pastebin.com/raw/XjDpyhzb",
   "url": "https://m1free.inwstream.com:1936/movie2/Jurassic Park 1-3/The Lost World Jurassic Park 2 (1997) th 1080p fw.mp4/playlist.m3u8",
   "referer": "https://fw4free.com/"
  },
  {
   "name": "Jurassic park 2 The lost world ใครว่ามันสูญพันธุ์ จูราสสิคพาร์ค (1997)",
   "info": "SoundTrack : SubThai",
   "image": "https://img.fw4free.com/postor/20200325124148Jurassic park 2 The lost world ใครว่ามันสูญพันธุ์ จูราสสิคพาร์ค(1997).jpg",
   "subtitle": "https://pastebin.com/raw/XjDpyhzb",
   "url": "https://m1free.inwstream.com:1936/movie2/Jurassic Park 1-3/The Lost World Jurassic Park 2 (1997) en 1080p fw.mp4/playlist.m3u8",
   "referer": "https://fw4free.com/"
  },
  {
   "name": "Jurassic park 3 จูราสสิคเวิลคลาส ไดโนเสาร์พันธุ์ดุ (2001)",
   "info": "พากย์ไทย",
   "image": "https://img.fw4free.com/postor/20200325123118Jurassic park 3 จูราสสิคเวิลคลาส ไดโนเสาร์พันธุ์ดุ (2001).jpeg",
   "subtitle": "https://pastebin.com/raw/XjDpyhzb",
   "url": "https://m1free.inwstream.com:1936/movie2/Jurassic Park 1-3/Jurassic Park 3 (2001) th 1080p fw.mp4/playlist.m3u8",
   "referer": "https://fw4free.com/"
  },
  {
   "name": "Jurassic park 3 จูราสสิคเวิลคลาส ไดโนเสาร์พันธุ์ดุ (2001)",
   "info": "SoundTrack : SubThai",
   "image": "https://img.fw4free.com/postor/20200325123118Jurassic park 3 จูราสสิคเวิลคลาส ไดโนเสาร์พันธุ์ดุ (2001).jpeg",
   "subtitle": "https://pastebin.com/raw/XjDpyhzb",
   "url": "https://m1free.inwstream.com:1936/movie2/Jurassic Park 1-3/Jurassic Park 3 (2001) en 1080p fw.mp4/playlist.m3u8",
   "referer": "https://fw4free.com/"
  }
]